Workbook
Name Slicer_Product_name: #N/A
Name Slicer_Store_ID: #N/A

Sheet Customer_Dim
A1: Customer_ID | B1: Name | C1: Age | D1: Gender | E1: City | F1: State | G1: Country | H1: Loyalty_Level
A2: CUST1000 | B2: Sheena Bonilla | C2: 55 | D2: Male | E2: Donaldton | F2: North Carolina | G2: USA | H2: NO DATA
A3: CUST1001 | B3: Eugene Nelson | C3: 26 | D3: Female | E3: Phillipsmouth | F3: North Dakota | G3: USA | H3: Platinum
A4: CUST1002 | B4: Dr. Benjamin Price | C4: 29 | D4: Female | E4: Kylebury | F4: Alabama | G4: USA | H4: Platinum
A5: CUST1003 | B5: Jeremy Harris | C5: 59 | D5: Female | E5: Thomastown | F5: Ohio | G5: USA | H5: Bronze
A6: CUST1004 | B6: Caroline Collins | C6: 64 | D6: Female | E6: Nicholasshire | F6: California | G6: USA | H6: Silver
A7: CUST1005 | B7: Christine Vaughn | C7: 24 | D7: Male | E7: East Amandamouth | F7: Oregon | G7: USA | H7: Bronze
A8: CUST1006 | B8: Amber Jackson | C8: 29 | D8: Female | E8: Deborahborough | F8: South Dakota | G8: USA | H8: Platinum
A9: CUST1007 | B9: Daniel Boyd | C9: 29 | D9: Female | E9: West Pamelafurt | F9: West Virginia | G9: USA | H9: Bronze
A10: CUST1008 | B10: Melissa Howard | C10: 53 | D10: Female | E10: Maynardton | F10: New Hampshire | G10: USA | H10: Gold
A11: CUST1009 | B11: Ms. Maria Leach | C11: 64 | D11: Male | E11: Melissashire | F11: Pennsylvania | G11: USA | H11: Platinum
A12: CUST1010 | B12: Dominic Page | C12: 53 | D12: Male | E12: Port Michaelburgh | F12: Pennsylvania | G12: USA | H12: Bronze
A13: CUST1011 | B13: Brian Lopez | C13: 28 | D13: Female | E13: East Krista | F13: New York | G13: USA | H13: Gold
... A501: CUST1499 | B501: Philip Pennington | C501: 27 | D501: Female | E501: East Valerieview | F501: Oregon | G501: USA | H501: Platinum

Sheet Product_Dim
A1: Product_ID | B1: Product_Name | C1: Category | D1: Sub_Category | E1: Brand | F1: Cost Imputed | G1: Stock
A2: PROD0 | B2: Brother Laser Printer | C2: Electronics | D2: Computer | E2: Hunt Inc | F2: 112.42 | G2: 416
A3: PROD1 | B3: Men's Graphic T-Shirt | C3: Clothing | D3: Tops | E3: Terry-Moore | F3: 342.56 | G3: 181
A4: PROD2 | B4: Women's Casual Hoodie | C4: Clothing | D4: Outerwear | E4: Sims Inc | F4: 296.82667 | G4: 352
A5: PROD3 | B5: Men's Running Jacket | C5: Clothing | D5: Outerwear | E5: Pineda Ltd | F5: 364.67 | G5: 452
A6: PROD4 | B6: Women's Yoga Pants | C6: Clothing | D6: Bottoms | E6: Gonzales-Davis | F6: 306.46 | G6: 487
A7: PROD5 | B7: Men's Leather Belt | C7: Clothing | D7: Accessories | E7: Baldwin, Garza and Gonzalez | F7: 261 | G7: 59
A8: PROD6 | B8: Herbal Face Moisturizer | C8: Beauty | D8: Skincare | E8: Davidson PLC | F8: 312.8 | G8: 350
A9: PROD7 | B9: LED Table Lamp | C9: Home | D9: Lighting | E9: Harrell LLC | F9: 218.86 | G9: 170
A10: PROD8 | B10: Wireless Bluetooth Earbuds | C10: Electronics | D10: Audio | E10: Perez-Johnston | F10: 439.07 | G10: 142
A11: PROD9 | B11: Adjustable Dumbbell Set | C11: Sports | D11: Fitness | E11: Hill PLC | F11: 495.72 | G11: 323
A12: PROD10 | B12: Ceramic Kitchen Bowl Set | C12: Home | D12: Kitchen | E12: Hamilton Group | F12: 298.86 | G12: 308
A13: PROD11 | B13: HD Smart TV Stick | C13: Electronics | D13: Accessories | E13: Gibson, Hobbs and Weaver | F13: 449.4
A14: PROD12 | B14: Hair Strengthening Shampoo | C14: Beauty | D14: Haircare | E14: Rice LLC | F14: 115.82 | G14: 460
A15: PROD13 | B15: USB-C Fast Charger | C15: Electronics | D15: Accessories | E15: Dawson-Perkins | F15: 242.23 | G15: 453
A16: PROD14 | B16: Decorative Wall Mirror | C16: Home | D16: Decor | E16: Luna, Anderson and Bowman | F16: 48.01 | G16: 439
A17: PROD15 | B17: 4K Home Projector | C17: Electronics | D17: Appliances | E17: Thomas LLC | F17: 465.34 | G17: 301
A18: PROD16 | B18: Beard Grooming Kit | C18: Beauty | D18: Grooming | E18: Erickson-Green | F18: 337.42 | G18: 256
A19: PROD17 | B19: Soccer Training Cone Set | C19: Sports | D19: Accessories | E19: Ford, Murphy and Wilson | F19: 144.53 | G19: 367
A20: PROD18 | B20: Women's Denim Jeans | C20: Clothing | D20: Bottoms | E20: Guerra-Hendrix | F20: 303.74667 | G20: 343
A21: PROD19 | B21: Knee Support Brace | C21: Sports | D21: Equipment | E21: May-Reese | F21: 21.34 | G21: 65
A22: PROD20 | B22: Outdoor Sports Water Bottle | C22: Sports | D22: Accessories | E22: Soto-Ellis | F22: 131.51
A23: PROD21 | B23: Multi-Purpose Storage Box | C23: Home | D23: Storage | E23: Gardner-Montes | F23: 123.46 | G23: 76
A24: PROD22 | B24: Carbon Fiber Tennis Racket | C24: Sports | D24: Equipment | E24: Flores, Pineda and Rodriguez | F24: 484.62 | G24: 432
A25: PROD23 | B25: Men's Formal Shirt | C25: Clothing | D25: Tops | E25: Moon, Mora and Santos | F25: 282.995 | G25: 360
A26: PROD24 | B26: Foldable Camping Chair | C26: Sports | D26: Outdoor | E26: Cook Ltd | F26: 166.06 | G26: 340
A27: PROD25 | B27: Women's Scarf Set | C27: Clothing | D27: Accessories | E27: Brown and Sons | F27: 174.02 | G27: 268
A28: PROD26 | B28: Wireless Bluetooth Speaker | C28: Electronics | D28: Audio | E28: Reed-Schmidt | F28: 322.41 | G28: 213
A29: PROD27 | B29: Decorative Floor Vase | C29: Home | D29: Decor | E29: Khan, Jones and Paul | F29: 219.12333 | G29: 378
A30: PROD28 | B30: Sports Stopwatch Timer | C30: Sports | D30: Accessories | E30: Burns-Hansen | F30: 38.76 | G30: 137
A31: PROD29 | B31: Fabric Sofa Throw Blanket | C31: Home | D31: Decor | E31: Hoffman Group | F31: 218.48 | G31: 276
A32: PROD30 | B32: Stainless Steel Cutlery Set | C32: Home | D32: Kitchen | E32: Stevens, Fernandez and Martin | F32: 19.52 | G32: 57
A33: PROD31 | B33: Basketball | C33: Sports | D33: Team Sports | E33: Nolan-Snow | F33: 204.39 | G33: 281
A34: PROD32 | B34: Vitamin C Face Serum | C34: Beauty | D34: Skincare | E34: Griffin Ltd | F34: 283.83 | G34: 244
... A56: PROD54 | B56: Sports Stopwatch Pro | C56: Sports | D56: Accessories | E56: Thompson-French | F56: 434.84 | G56: 185
A57: PROD55 | B57: Ceramic Plant Pot | C57: Home | D57: Decor | E57: Hatfield, Baird and Torres | F57: 81.75
A58: PROD56 | B58: Premium Blanket Throw | C58: Home | D58: Decor | E58: Hernandez, Kennedy and Porter | F58: 461.47 | G58: 190
A59: PROD57 | B59: Foam Roller | C59: Sports | D59: Fitness | E59: Atkinson, Camacho and Oliver | F59: 30.62 | G59: 138
A60: PROD58 | B60: Womens Cotton Scarf | C60: Clothing | D60: Accessories | E60: Shepherd-Gould | F60: 113.83 | G60: 485
A61: PROD59 | B61: Men's Hair Styling Gel | C61: Beauty | D61: Haircare | E61: Cline-Mccarthy | F61: 17.31 | G61: 399
A62: PROD60 | B62: Luxury Perfume Spray | C62: Beauty | D62: Fragrance | E62: Gibson, Green and Lopez | F62: 482.75 | G62: 444
A63: PROD61 | B63: Tennis Ball 3-Pack | C63: Sports | D63: Equipment | E63: Lopez LLC | F63: 103.45 | G63: 465
A64: PROD62 | B64: Laptop Cooling Pad | C64: Electronics | D64: Computer | E64: Murray, Gould and Ware | F64: 86.42 | G64: 222
A65: PROD63 | B65: Organic Sunscreen Lotion | C65: Beauty | D65: Skincare | E65: Anderson-Riley | F65: 266.86 | G65: 458
A66: PROD64 | B66: Matte Lipstick Set | C66: Beauty | D66: Makeup | E66: Zhang Inc | F66: 299.11 | G66: 118
A67: PROD65 | B67: Adjustable Dumbbells 20kg | C67: Sports | D67: Fitness | E67: Montgomery, Benton and Miller | F67: 240.63 | G67: 423
A68: PROD66 | B68: Women's Hair Dryer Brush | C68: Beauty | D68: Haircare | E68: Torres, Spencer and Potter | F68: 340.39 | G68: 177
A69: PROD67 | B69: Smart LED Light Strip | C69: Electronics | D69: Accessories | E69: Flores-Davis | F69: 349.17 | G69: 476
... A101: PROD99 | B101: Stainless Steel Cookware Set | C101: Home | D101: Kitchen | E101: Campbell Ltd | F101: 201.41 | G101: 146

Sheet Store_Dim
A1: Store_ID | B1: Store_Name | C1: Region | D1: City | E1: Store_Type
A2: STORE0 | B2: Rivera-Warner | C2: East | D2: Washingtonfurt | E2: Flagship
A3: STORE1 | B3: Martinez, Adkins and Johnson | C3: North | D3: Danielmouth | E3: Flagship
A4: STORE2 | B4: Black-Horn | C4: South | D4: North Nancyview | E4: Outlet
A5: STORE3 | B5: Johnson-Wright | C5: North | D5: Hoodberg | E5: Outlet
A6: STORE4 | B6: Alexander Group | C6: South | D6: Port Sharon | E6: Online
A7: STORE5 | B7: Gray Ltd | C7: North | D7: New Michaelchester | E7: Outlet
A8: STORE6 | B8: Benson-Elliott | C8: East | D8: Port Josephberg | E8: Online
A9: STORE7 | B9: Martinez-Mullins | C9: South | D9: Williamsfurt | E9: Online
A10: STORE8 | B10: Bean, Jones and Park | C10: West | D10: Thompsonborough | E10: Online
A11: STORE9 | B11: Moore, Padilla and Butler | C11: South | D11: East Johnstad | E11: Flagship
A12: STORE10 | B12: Hill, Wagner and Ballard | C12: East | D12: East Davidville | E12: Online
... A21: STORE19 | B21: Mann-Austin | C21: East | D21: Vasquezborough | E21: Online

Sheet Sales_Fact
A1: Sales_ID | B1: Order_Date | C1: Customer_ID | D1: Product_ID | E1: Store_ID | F1: Quantity | G1: Unit_Price | H1: Discount | I1: Payment_Type | J1: Total_Amount Imputed | K1: Quantity Imputed | L1: Unit_Price imputed | M1: Discount Imputed | N1: Total_Amount Imputed
A2: SALE261 | B2: 45742 | C2: CUST1333 | D2: PROD0 | E2: STORE8 | F2: 4 | G2: 849.21 | H2: 0.07 | I2: Credit Card | J2: 3159.0612 | K2: =IF(ISBLANK(F2),J2/(G2*(1-H2)),F2) -> 4 | L2: =IF(ISBLANK(G2),J2/(F2*(1-H2)),G2) -> 849.21 | M2: =IF(ISBLANK(H2),1-(J2/(L2*F2)),H2) -> 0.07 | N2: =IF(ISBLANK(J2),F2*G2*(1-H2),J2) -> 3159.0612
A3: SALE426 | B3: 45462 | C3: CUST1175 | D3: PROD0 | E3: STORE16 | F3: 4 | G3: 897.93 | H3: 0.05 | I3: COD | J3: 3412.134 | K3: =IF(ISBLANK(F3),J3/(G3*(1-H3)),F3) -> 4 | L3: =IF(ISBLANK(G3),J3/(F3*(1-H3)),G3) -> 897.93 | M3: =IF(ISBLANK(H3),1-(J3/(L3*F3)),H3) -> 0.05 | N3: =IF(ISBLANK(J3),F3*G3*(1-H3),J3) -> 3412.134
A4: SALE514 | B4: 45312 | C4: CUST1129 | D4: PROD0 | E4: STORE7 | F4: 4 | G4: 191.65 | H4: 0.19 | I4: PayPal | J4: 620.946 | K4: =IF(ISBLANK(F4),J4/(G4*(1-H4)),F4) -> 4 | L4: =IF(ISBLANK(G4),J4/(F4*(1-H4)),G4) -> 191.65 | M4: =IF(ISBLANK(H4),1-(J4/(L4*F4)),H4) -> 0.19 | N4: =IF(ISBLANK(J4),F4*G4*(1-H4),J4) -> 620.946
A5: SALE1004 | B5: 45834 | C5: CUST1300 | D5: PROD0 | E5: STORE17 | F5: 1 | G5: 522.69 | H5: 0.06 | I5: COD | J5: 491.3286 | K5: =IF(ISBLANK(F5),J5/(G5*(1-H5)),F5) -> 1 | L5: =IF(ISBLANK(G5),J5/(F5*(1-H5)),G5) -> 522.69 | M5: =IF(ISBLANK(H5),1-(J5/(L5*F5)),H5) -> 0.06 | N5: =IF(ISBLANK(J5),F5*G5*(1-H5),J5) -> 491.3286
A6: SALE1097 | B6: 45596 | C6: CUST1071 | D6: PROD0 | E6: STORE3 | F6: 2 | G6: 374.42 | H6: 0.21 | I6: COD | J6: 591.5836 | K6: =IF(ISBLANK(F6),J6/(G6*(1-H6)),F6) -> 2 | L6: =IF(ISBLANK(G6),J6/(F6*(1-H6)),G6) -> 374.42 | M6: =IF(ISBLANK(H6),1-(J6/(L6*F6)),H6) -> 0.21 | N6: =IF(ISBLANK(J6),F6*G6*(1-H6),J6) -> 591.5836
A7: SALE1121 | B7: 45579 | C7: CUST1319 | D7: PROD0 | E7: STORE4 | F7: 3 | G7: 819.93 | H7: 0.08 | I7: PayPal | J7: 2263.0068 | K7: =IF(ISBLANK(F7),J7/(G7*(1-H7)),F7) -> 3 | L7: =IF(ISBLANK(G7),J7/(F7*(1-H7)),G7) -> 819.93 | M7: =IF(ISBLANK(H7),1-(J7/(L7*F7)),H7) -> 0.08 | N7: =IF(ISBLANK(J7),F7*G7*(1-H7),J7) -> 2263.0068
A8: SALE1126 | B8: 45653 | C8: CUST1379 | D8: PROD0 | E8: STORE17 | F8: 3 | G8: 241.64 | H8: 0.29 | I8: PayPal | J8: 514.6932 | K8: =IF(ISBLANK(F8),J8/(G8*(1-H8)),F8) -> 3 | L8: =IF(ISBLANK(G8),J8/(F8*(1-H8)),G8) -> 241.64 | M8: =IF(ISBLANK(H8),1-(J8/(L8*F8)),H8) -> 0.29 | N8: =IF(ISBLANK(J8),F8*G8*(1-H8),J8) -> 514.6932
A9: SALE1190 | B9: 45468 | C9: CUST1443 | D9: PROD0 | E9: STORE9 | F9: 2 | G9: 540.48 | H9: 0.29 | I9: Credit Card | J9: 767.4816 | K9: =IF(ISBLANK(F9),J9/(G9*(1-H9)),F9) -> 2 | L9: =IF(ISBLANK(G9),J9/(F9*(1-H9)),G9) -> 540.48 | M9: =IF(ISBLANK(H9),1-(J9/(L9*F9)),H9) -> 0.29 | N9: =IF(ISBLANK(J9),F9*G9*(1-H9),J9) -> 767.4816
A10: SALE1277 | B10: 45524 | C10: CUST1003 | D10: PROD0 | E10: STORE14 | F10: 1 | G10: 449.6 | H10: 0.01 | I10: PayPal | J10: 445.104 | K10: =IF(ISBLANK(F10),J10/(G10*(1-H10)),F10) -> 1 | L10: =IF(ISBLANK(G10),J10/(F10*(1-H10)),G10) -> 449.6 | M10: =IF(ISBLANK(H10),1-(J10/(L10*F10)),H10) -> 0.01 | N10: =IF(ISBLANK(J10),F10*G10*(1-H10),J10) -> 445.104
A11: SALE1286 | B11: 45810 | C11: CUST1365 | D11: PROD0 | E11: STORE16 | F11: 3 | G11: 279.45 | H11: 0.15 | I11: COD | J11: 712.5975 | K11: =IF(ISBLANK(F11),J11/(G11*(1-H11)),F11) -> 3 | L11: =IF(ISBLANK(G11),J11/(F11*(1-H11)),G11) -> 279.45 | M11: =IF(ISBLANK(H11),1-(J11/(L11*F11)),H11) -> 0.15 | N11: =IF(ISBLANK(J11),F11*G11*(1-H11),J11) -> 712.5975
A12: SALE1314 | B12: 45523 | C12: CUST1008 | D12: PROD0 | E12: STORE9 | F12: 2 | G12: 943.8 | H12: 0.06 | I12: Credit Card | J12: 1774.344 | K12: =IF(ISBLANK(F12),J12/(G12*(1-H12)),F12) -> 2 | L12: =IF(ISBLANK(G12),J12/(F12*(1-H12)),G12) -> 943.8 | M12: =IF(ISBLANK(H12),1-(J12/(L12*F12)),H12) -> 0.06 | N12: =IF(ISBLANK(J12),F12*G12*(1-H12),J12) -> 1774.344
A13: SALE1627 | B13: 45885 | C13: CUST1147 | D13: PROD0 | E13: STORE16 | F13: 3 | G13: 60.26 | H13: 0.04 | I13: Credit Card | J13: 173.5488 | K13: =IF(ISBLANK(F13),J13/(G13*(1-H13)),F13) -> 3 | L13: =IF(ISBLANK(G13),J13/(F13*(1-H13)),G13) -> 60.26 | M13: =IF(ISBLANK(H13),1-(J13/(L13*F13)),H13) -> 0.04 | N13: =IF(ISBLANK(J13),F13*G13*(1-H13),J13) -> 173.5488
... A132: SALE5 | B132: 45499 | C132: CUST1116 | D132: PROD15 | E132: STORE7 | F132: 3 | G132: 147.01 | H132: 0.19 | I132: COD | J132: 357.2343 | K132: =IF(ISBLANK(F132),J132/(G132*(1-H132)),F132) -> 3 | L132: =IF(ISBLANK(G132),J132/(F132*(1-H132)),G132) -> 147.01 | M132: =IF(ISBLANK(H132),1-(J132/(L132*F132)),H132) -> 0.19 | N132: =IF(ISBLANK(J132),F132*G132*(1-H132),J132) -> 357.2343
A133: SALE58 | B133: 45633 | C133: CUST1404 | D133: PROD15 | E133: STORE7 | F133: 4 | G133: 733.42 | I133: PayPal | J133: 2552.3016 | K133: =IF(ISBLANK(F133),J133/(G133*(1-H133)),F133) -> 4 | L133: =IF(ISBLANK(G133),J133/(F133*(1-H133)),G133) -> 733.42 | M133: =IF(ISBLANK(H133),1-(J133/(L133*F133)),H133) -> 0.13 | N133: =IF(ISBLANK(J133),F133*G133*(1-H133),J133) -> 2552.3016
A134: SALE217 | B134: 45219 | C134: CUST1266 | D134: PROD15 | E134: STORE19 | F134: 1 | G134: 332.82 | H134: 0.14 | I134: PayPal | J134: 286.2252 | K134: =IF(ISBLANK(F134),J134/(G134*(1-H134)),F134) -> 1 | L134: =IF(ISBLANK(G134),J134/(F134*(1-H134)),G134) -> 332.82 | M134: =IF(ISBLANK(H134),1-(J134/(L134*F134)),H134) -> 0.14 | N134: =IF(ISBLANK(J134),F134*G134*(1-H134),J134) -> 286.2252
A135: SALE238 | B135: 45253 | C135: CUST1135 | D135: PROD15 | E135: STORE5 | F135: 1 | G135: 594.44 | H135: 0.21 | I135: Credit Card | J135: 469.6076 | K135: =IF(ISBLANK(F135),J135/(G135*(1-H135)),F135) -> 1 | L135: =IF(ISBLANK(G135),J135/(F135*(1-H135)),G135) -> 594.44 | M135: =IF(ISBLANK(H135),1-(J135/(L135*F135)),H135) -> 0.21 | N135: =IF(ISBLANK(J135),F135*G135*(1-H135),J135) -> 469.6076
A136: SALE347 | B136: 45541 | C136: CUST1054 | D136: PROD15 | E136: STORE15 | F136: 2 | G136: 280.37 | H136: 0.22 | I136: COD | J136: 437.3772 | K136: =IF(ISBLANK(F136),J136/(G136*(1-H136)),F136) -> 2 | L136: =IF(ISBLANK(G136),J136/(F136*(1-H136)),G136) -> 280.37 | M136: =IF(ISBLANK(H136),1-(J136/(L136*F136)),H136) -> 0.22 | N136: =IF(ISBLANK(J136),F136*G136*(1-H136),J136) -> 437.3772
A137: SALE355 | B137: 45304 | C137: CUST1241 | D137: PROD15 | E137: STORE15 | F137: 2 | G137: 899.27 | H137: 0.17 | I137: Credit Card | J137: 1492.7882 | K137: =IF(ISBLANK(F137),J137/(G137*(1-H137)),F137) -> 2 | L137: =IF(ISBLANK(G137),J137/(F137*(1-H137)),G137) -> 899.27 | M137: =IF(ISBLANK(H137),1-(J137/(L137*F137)),H137) -> 0.17 | N137: =IF(ISBLANK(J137),F137*G137*(1-H137),J137) -> 1492.7882
A138: SALE409 | B138: 45837 | C138: CUST1327 | D138: PROD15 | E138: STORE16 | F138: 4 | G138: 370.63 | H138: 0.08 | I138: Credit Card | J138: 1363.9184 | K138: =IF(ISBLANK(F138),J138/(G138*(1-H138)),F138) -> 4 | L138: =IF(ISBLANK(G138),J138/(F138*(1-H138)),G138) -> 370.63 | M138: =IF(ISBLANK(H138),1-(J138/(L138*F138)),H138) -> 0.08 | N138: =IF(ISBLANK(J138),F138*G138*(1-H138),J138) -> 1363.9184
A139: SALE479 | B139: 45574 | C139: CUST1449 | D139: PROD15 | E139: STORE9 | F139: 3 | G139: 635.13 | H139: 0.09 | I139: PayPal | J139: 1733.9049 | K139: =IF(ISBLANK(F139),J139/(G139*(1-H139)),F139) -> 3 | L139: =IF(ISBLANK(G139),J139/(F139*(1-H139)),G139) -> 635.13 | M139: =IF(ISBLANK(H139),1-(J139/(L139*F139)),H139) -> 0.09 | N139: =IF(ISBLANK(J139),F139*G139*(1-H139),J139) -> 1733.9049
A140: SALE609 | B140: 45921 | C140: CUST1470 | D140: PROD15 | E140: STORE1 | F140: 4 | G140: 479.11 | H140: 0.24 | I140: PayPal | J140: 1456.4944 | K140: =IF(ISBLANK(F140),J140/(G140*(1-H140)),F140) -> 4 | L140: =IF(ISBLANK(G140),J140/(F140*(1-H140)),G140) -> 479.11 | M140: =IF(ISBLANK(H140),1-(J140/(L140*F140)),H140) -> 0.24 | N140: =IF(ISBLANK(J140),F140*G140*(1-H140),J140) -> 1456.4944
A141: SALE658 | B141: 45629 | C141: CUST1055 | D141: PROD15 | E141: STORE6 | F141: 2 | G141: 884.48 | H141: 0 | I141: COD | J141: 1768.96 | K141: =IF(ISBLANK(F141),J141/(G141*(1-H141)),F141) -> 2 | L141: =IF(ISBLANK(G141),J141/(F141*(1-H141)),G141) -> 884.48 | M141: =IF(ISBLANK(H141),1-(J141/(L141*F141)),H141) -> 0 | N141: =IF(ISBLANK(J141),F141*G141*(1-H141),J141) -> 1768.96
A142: SALE697 | B142: 45832 | C142: CUST1139 | D142: PROD15 | E142: STORE18 | F142: 2 | G142: 669.12 | H142: 0.22 | I142: Credit Card | J142: 1043.8272 | K142: =IF(ISBLANK(F142),J142/(G142*(1-H142)),F142) -> 2 | L142: =IF(ISBLANK(G142),J142/(F142*(1-H142)),G142) -> 669.12 | M142: =IF(ISBLANK(H142),1-(J142/(L142*F142)),H142) -> 0.22 | N142: =IF(ISBLANK(J142),F142*G142*(1-H142),J142) -> 1043.8272
A143: SALE703 | B143: 45429 | C143: CUST1196 | D143: PROD15 | E143: STORE16 | F143: 3 | G143: 262.69 | H143: 0.04 | I143: PayPal | J143: 756.5472 | K143: =IF(ISBLANK(F143),J143/(G143*(1-H143)),F143) -> 3 | L143: =IF(ISBLANK(G143),J143/(F143*(1-H143)),G143) -> 262.69 | M143: =IF(ISBLANK(H143),1-(J143/(L143*F143)),H143) -> 0.04 | N143: =IF(ISBLANK(J143),F143*G143*(1-H143),J143) -> 756.5472
A144: SALE722 | B144: 45379 | C144: CUST1241 | D144: PROD15 | E144: STORE14 | F144: 1 | G144: 31.36 | H144: 0.21 | I144: COD | J144: 24.7744 | K144: =IF(ISBLANK(F144),J144/(G144*(1-H144)),F144) -> 1 | L144: =IF(ISBLANK(G144),J144/(F144*(1-H144)),G144) -> 31.36 | M144: =IF(ISBLANK(H144),1-(J144/(L144*F144)),H144) -> 0.21 | N144: =IF(ISBLANK(J144),F144*G144*(1-H144),J144) -> 24.7744
A145: SALE914 | B145: 45308 | C145: CUST1039 | D145: PROD15 | E145: STORE19 | F145: 3 | G145: 620.12 | H145: 0.06 | I145: Credit Card | J145: 1748.7384 | K145: =IF(ISBLANK(F145),J145/(G145*(1-H145)),F145) -> 3 | L145: =IF(ISBLANK(G145),J145/(F145*(1-H145)),G145) -> 620.12 | M145: =IF(ISBLANK(H145),1-(J145/(L145*F145)),H145) -> 0.06 | N145: =IF(ISBLANK(J145),F145*G145*(1-H145),J145) -> 1748.7384
... A585: SALE258 | B585: 45300 | C585: CUST1136 | D585: PROD35 | E585: STORE17 | F585: 1 | G585: 222.94 | H585: 0.19 | I585: Credit Card | J585: 180.5814 | K585: =IF(ISBLANK(F585),J585/(G585*(1-H585)),F585) -> 1 | L585: =IF(ISBLANK(G585),J585/(F585*(1-H585)),G585) -> 222.94 | M585: =IF(ISBLANK(H585),1-(J585/(L585*F585)),H585) -> 0.19 | N585: =IF(ISBLANK(J585),F585*G585*(1-H585),J585) -> 180.5814
A586: SALE259 | B586: 45773 | C586: CUST1248 | D586: PROD35 | E586: STORE2 | F586: 2 | G586: 355.3 | I586: PayPal | J586: 589.798 | K586: =IF(ISBLANK(F586),J586/(G586*(1-H586)),F586) -> 2 | L586: =IF(ISBLANK(G586),J586/(F586*(1-H586)),G586) -> 355.3 | M586: =IF(ISBLANK(H586),1-(J586/(L586*F586)),H586) -> 0.17 | N586: =IF(ISBLANK(J586),F586*G586*(1-H586),J586) -> 589.798
A587: SALE364 | B587: 45723 | C587: CUST1216 | D587: PROD35 | E587: STORE18 | F587: 1 | G587: 213.69 | H587: 0.28 | I587: COD | J587: 153.8568 | K587: =IF(ISBLANK(F587),J587/(G587*(1-H587)),F587) -> 1 | L587: =IF(ISBLANK(G587),J587/(F587*(1-H587)),G587) -> 213.69 | M587: =IF(ISBLANK(H587),1-(J587/(L587*F587)),H587) -> 0.28 | N587: =IF(ISBLANK(J587),F587*G587*(1-H587),J587) -> 153.8568
A588: SALE543 | B588: 45711 | C588: CUST1333 | D588: PROD35 | E588: STORE6 | F588: 1 | G588: 763.34 | H588: 0.11 | I588: COD | J588: 679.3726 | K588: =IF(ISBLANK(F588),J588/(G588*(1-H588)),F588) -> 1 | L588: =IF(ISBLANK(G588),J588/(F588*(1-H588)),G588) -> 763.34 | M588: =IF(ISBLANK(H588),1-(J588/(L588*F588)),H588) -> 0.11 | N588: =IF(ISBLANK(J588),F588*G588*(1-H588),J588) -> 679.3726
A589: SALE946 | B589: 45600 | C589: CUST1140 | D589: PROD35 | E589: STORE1 | F589: 2 | G589: 157.18 | H589: 0.15 | I589: Credit Card | J589: 267.206 | K589: =IF(ISBLANK(F589),J589/(G589*(1-H589)),F589) -> 2 | L589: =IF(ISBLANK(G589),J589/(F589*(1-H589)),G589) -> 157.18 | M589: =IF(ISBLANK(H589),1-(J589/(L589*F589)),H589) -> 0.15 | N589: =IF(ISBLANK(J589),F589*G589*(1-H589),J589) -> 267.206
A590: SALE1054 | B590: 45850 | C590: CUST1437 | D590: PROD35 | E590: STORE12 | F590: 3 | G590: 471.31 | H590: 0 | I590: PayPal | J590: 1413.93 | K590: =IF(ISBLANK(F590),J590/(G590*(1-H590)),F590) -> 3 | L590: =IF(ISBLANK(G590),J590/(F590*(1-H590)),G590) -> 471.31 | M590: =IF(ISBLANK(H590),1-(J590/(L590*F590)),H590) -> 0 | N590: =IF(ISBLANK(J590),F590*G590*(1-H590),J590) -> 1413.93
A591: SALE1165 | B591: 45251 | C591: CUST1243 | D591: PROD35 | E591: STORE0 | F591: 2 | G591: 961.68 | H591: 0.27 | I591: PayPal | J591: 1404.0528 | K591: =IF(ISBLANK(F591),J591/(G591*(1-H591)),F591) -> 2 | L591: =IF(ISBLANK(G591),J591/(F591*(1-H591)),G591) -> 961.68 | M591: =IF(ISBLANK(H591),1-(J591/(L591*F591)),H591) -> 0.27 | N591: =IF(ISBLANK(J591),F591*G591*(1-H591),J591) -> 1404.0528
A592: SALE1211 | B592: 45558 | C592: CUST1015 | D592: PROD35 | E592: STORE6 | F592: 4 | G592: 328.27 | H592: 0.09 | I592: PayPal | J592: 1194.9028 | K592: =IF(ISBLANK(F592),J592/(G592*(1-H592)),F592) -> 4 | L592: =IF(ISBLANK(G592),J592/(F592*(1-H592)),G592) -> 328.27 | M592: =IF(ISBLANK(H592),1-(J592/(L592*F592)),H592) -> 0.09 | N592: =IF(ISBLANK(J592),F592*G592*(1-H592),J592) -> 1194.9028
A593: SALE1219 | B593: 45905 | C593: CUST1030 | D593: PROD35 | E593: STORE15 | F593: 4 | G593: 642.05 | H593: 0.25 | I593: Credit Card | J593: 1926.15 | K593: =IF(ISBLANK(F593),J593/(G593*(1-H593)),F593) -> 4 | L593: =IF(ISBLANK(G593),J593/(F593*(1-H593)),G593) -> 642.05 | M593: =IF(ISBLANK(H593),1-(J593/(L593*F593)),H593) -> 0.25 | N593: =IF(ISBLANK(J593),F593*G593*(1-H593),J593) -> 1926.15
A594: SALE1369 | B594: 45798 | C594: CUST1005 | D594: PROD35 | E594: STORE7 | F594: 4 | G594: 185.67 | H594: 0.21 | I594: PayPal | J594: 586.7172 | K594: =IF(ISBLANK(F594),J594/(G594*(1-H594)),F594) -> 4 | L594: =IF(ISBLANK(G594),J594/(F594*(1-H594)),G594) -> 185.67 | M594: =IF(ISBLANK(H594),1-(J594/(L594*F594)),H594) -> 0.21 | N594: =IF(ISBLANK(J594),F594*G594*(1-H594),J594) -> 586.7172
A595: SALE1410 | B595: 45760 | C595: CUST1144 | D595: PROD35 | E595: STORE4 | F595: 2 | G595: 326.85 | H595: 0.17 | I595: COD | J595: 542.571 | K595: =IF(ISBLANK(F595),J595/(G595*(1-H595)),F595) -> 2 | L595: =IF(ISBLANK(G595),J595/(F595*(1-H595)),G595) -> 326.85 | M595: =IF(ISBLANK(H595),1-(J595/(L595*F595)),H595) -> 0.17 | N595: =IF(ISBLANK(J595),F595*G595*(1-H595),J595) -> 542.571
A596: SALE1451 | B596: 45383 | C596: CUST1005 | D596: PROD35 | E596: STORE18 | F596: 3 | G596: 341.51 | H596: 0.22 | I596: COD | J596: 799.1334 | K596: =IF(ISBLANK(F596),J596/(G596*(1-H596)),F596) -> 3 | L596: =IF(ISBLANK(G596),J596/(F596*(1-H596)),G596) -> 341.51 | M596: =IF(ISBLANK(H596),1-(J596/(L596*F596)),H596) -> 0.22 | N596: =IF(ISBLANK(J596),F596*G596*(1-H596),J596) -> 799.1334
A597: SALE1506 | B597: 45864 | C597: CUST1469 | D597: PROD35 | E597: STORE8 | F597: 4 | G597: 480.75 | H597: 0.02 | I597: Credit Card | J597: 1884.54 | K597: =IF(ISBLANK(F597),J597/(G597*(1-H597)),F597) -> 4 | L597: =IF(ISBLANK(G597),J597/(F597*(1-H597)),G597) -> 480.75 | M597: =IF(ISBLANK(H597),1-(J597/(L597*F597)),H597) -> 0.02 | N597: =IF(ISBLANK(J597),F597*G597*(1-H597),J597) -> 1884.54
A598: SALE1810 | B598: 45520 | C598: CUST1306 | D598: PROD35 | E598: STORE7 | F598: 1 | G598: 617.4 | H598: 0.21 | I598: Credit Card | J598: 487.746 | K598: =IF(ISBLANK(F598),J598/(G598*(1-H598)),F598) -> 1 | L598: =IF(ISBLANK(G598),J598/(F598*(1-H598)),G598) -> 617.4 | M598: =IF(ISBLANK(H598),1-(J598/(L598*F598)),H598) -> 0.21 | N598: =IF(ISBLANK(J598),F598*G598*(1-H598),J598) -> 487.746
... A604: SALE144 | B604: 45448 | C604: CUST1435 | D604: PROD36 | E604: STORE8 | F604: 3 | G604: 237.24 | H604: 0.24 | I604: PayPal | J604: 540.9072 | K604: =IF(ISBLANK(F604),J604/(G604*(1-H604)),F604) -> 3 | L604: =IF(ISBLANK(G604),J604/(F604*(1-H604)),G604) -> 237.24 | M604: =IF(ISBLANK(H604),1-(J604/(L604*F604)),H604) -> 0.24 | N604: =IF(ISBLANK(J604),F604*G604*(1-H604),J604) -> 540.9072
A605: SALE146 | B605: 45626 | C605: CUST1443 | D605: PROD36 | E605: STORE19 | F605: 3 | G605: 584.41 | H605: 0 | I605: COD | J605: 1753.23 | K605: =IF(ISBLANK(F605),J605/(G605*(1-H605)),F605) -> 3 | L605: =IF(ISBLANK(G605),J605/(F605*(1-H605)),G605) -> 584.41 | M605: =IF(H605="0",1-(J605/(L605*F605)),H605) -> 0 | N605: =IF(ISBLANK(J605),F605*G605*(1-H605),J605) -> 1753.23
A606: SALE332 | B606: 45815 | C606: CUST1133 | D606: PROD36 | E606: STORE4 | F606: 3 | G606: 399.42 | H606: 0.02 | I606: Credit Card | J606: 1174.2948 | K606: =IF(ISBLANK(F606),J606/(G606*(1-H606)),F606) -> 3 | L606: =IF(ISBLANK(G606),J606/(F606*(1-H606)),G606) -> 399.42 | M606: =IF(ISBLANK(H606),1-(J606/(L606*F606)),H606) -> 0.02 | N606: =IF(ISBLANK(J606),F606*G606*(1-H606),J606) -> 1174.2948
A607: SALE464 | B607: 45938 | C607: CUST1300 | D607: PROD36 | E607: STORE14 | F607: 1 | G607: 850.83 | H607: 0.28 | I607: PayPal | J607: 612.5976 | K607: =IF(ISBLANK(F607),J607/(G607*(1-H607)),F607) -> 1 | L607: =IF(ISBLANK(G607),J607/(F607*(1-H607)),G607) -> 850.83 | M607: =IF(ISBLANK(H607),1-(J607/(L607*F607)),H607) -> 0.28 | N607: =IF(ISBLANK(J607),F607*G607*(1-H607),J607) -> 612.5976
A608: SALE489 | B608: 45644 | C608: CUST1275 | D608: PROD36 | E608: STORE6 | F608: 2 | G608: 992.55 | H608: 0.28 | I608: Credit Card | J608: 1429.272 | K608: =IF(ISBLANK(F608),J608/(G608*(1-H608)),F608) -> 2 | L608: =IF(ISBLANK(G608),J608/(F608*(1-H608)),G608) -> 992.55 | M608: =IF(ISBLANK(H608),1-(J608/(L608*F608)),H608) -> 0.28 | N608: =IF(ISBLANK(J608),F608*G608*(1-H608),J608) -> 1429.272
A609: SALE656 | B609: 45397 | C609: CUST1219 | D609: PROD36 | E609: STORE17 | F609: 2 | G609: 637.56 | H609: 0.05 | I609: COD | J609: 1211.364 | K609: =IF(ISBLANK(F609),J609/(G609*(1-H609)),F609) -> 2 | L609: =IF(ISBLANK(G609),J609/(F609*(1-H609)),G609) -> 637.56 | M609: =IF(ISBLANK(H609),1-(J609/(L609*F609)),H609) -> 0.05 | N609: =IF(ISBLANK(J609),F609*G609*(1-H609),J609) -> 1211.364
A610: SALE957 | B610: 45761 | C610: CUST1187 | D610: PROD36 | E610: STORE8 | F610: 1 | G610: 579.69 | H610: 0.02 | I610: Credit Card | J610: 568.0962 | K610: =IF(ISBLANK(F610),J610/(G610*(1-H610)),F610) -> 1 | L610: =IF(ISBLANK(G610),J610/(F610*(1-H610)),G610) -> 579.69 | M610: =IF(ISBLANK(H610),1-(J610/(L610*F610)),H610) -> 0.02 | N610: =IF(ISBLANK(J610),F610*G610*(1-H610),J610) -> 568.0962
A611: SALE1182 | B611: 45321 | C611: CUST1453 | D611: PROD36 | E611: STORE7 | F611: 1 | G611: 514.65 | H611: 0.18 | I611: Credit Card | J611: 422.013 | K611: =IF(ISBLANK(F611),J611/(G611*(1-H611)),F611) -> 1 | L611: =IF(ISBLANK(G611),J611/(F611*(1-H611)),G611) -> 514.65 | M611: =IF(ISBLANK(H611),1-(J611/(L611*F611)),H611) -> 0.18 | N611: =IF(ISBLANK(J611),F611*G611*(1-H611),J611) -> 422.013
A612: SALE1210 | B612: 45530 | C612: CUST1081 | D612: PROD36 | E612: STORE8 | F612: 4 | G612: 271.04 | H612: 0.12 | I612: COD | J612: 954.0608 | K612: =IF(ISBLANK(F612),J612/(G612*(1-H612)),F612) -> 4 | L612: =IF(ISBLANK(G612),J612/(F612*(1-H612)),G612) -> 271.04 | M612: =IF(ISBLANK(H612),1-(J612/(L612*F612)),H612) -> 0.12 | N612: =IF(ISBLANK(J612),F612*G612*(1-H612),J612) -> 954.0608
A613: SALE1254 | B613: 45543 | C613: CUST1212 | D613: PROD36 | E613: STORE11 | F613: 3 | G613: 120.67 | H613: 0.08 | I613: COD | J613: 333.0492 | K613: =IF(ISBLANK(F613),J613/(G613*(1-H613)),F613) -> 3 | L613: =IF(ISBLANK(G613),J613/(F613*(1-H613)),G613) -> 120.67 | M613: =IF(ISBLANK(H613),1-(J613/(L613*F613)),H613) -> 0.08 | N613: =IF(ISBLANK(J613),F613*G613*(1-H613),J613) -> 333.0492
A614: SALE1289 | B614: 45537 | C614: CUST1177 | D614: PROD36 | E614: STORE9 | F614: 2 | G614: 117.34 | H614: 0.09 | I614: PayPal | J614: 213.5588 | K614: =IF(ISBLANK(F614),J614/(G614*(1-H614)),F614) -> 2 | L614: =IF(ISBLANK(G614),J614/(F614*(1-H614)),G614) -> 117.34 | M614: =IF(ISBLANK(H614),1-(J614/(L614*F614)),H614) -> 0.09 | N614: =IF(ISBLANK(J614),F614*G614*(1-H614),J614) -> 213.5588
A615: SALE1556 | B615: 45606 | C615: CUST1493 | D615: PROD36 | E615: STORE0 | F615: 1 | G615: 887.38 | H615: 0.01 | I615: COD | J615: 878.5062 | K615: =IF(ISBLANK(F615),J615/(G615*(1-H615)),F615) -> 1 | L615: =IF(ISBLANK(G615),J615/(F615*(1-H615)),G615) -> 887.38 | M615: =IF(ISBLANK(H615),1-(J615/(L615*F615)),H615) -> 0.01 | N615: =IF(ISBLANK(J615),F615*G615*(1-H615),J615) -> 878.5062
A616: SALE1589 | B616: 45235 | C616: CUST1034 | D616: PROD36 | E616: STORE4 | F616: 3 | G616: 811.45 | H616: 0.26 | I616: Credit Card | J616: 1801.419 | K616: =IF(ISBLANK(F616),J616/(G616*(1-H616)),F616) -> 3 | L616: =IF(ISBLANK(G616),J616/(F616*(1-H616)),G616) -> 811.45 | M616: =IF(ISBLANK(H616),1-(J616/(L616*F616)),H616) -> 0.26 | N616: =IF(ISBLANK(J616),F616*G616*(1-H616),J616) -> 1801.419
A617: SALE1734 | B617: 45843 | C617: CUST1202 | D617: PROD36 | E617: STORE13 | F617: 2 | G617: 208.09 | H617: 0.27 | I617: Credit Card | J617: 303.8114 | K617: =IF(ISBLANK(F617),J617/(G617*(1-H617)),F617) -> 2 | L617: =IF(ISBLANK(G617),J617/(F617*(1-H617)),G617) -> 208.09 | M617: =IF(ISBLANK(H617),1-(J617/(L617*F617)),H617) -> 0.27 | N617: =IF(ISBLANK(J617),F617*G617*(1-H617),J617) -> 303.8114
... A1127: SALE1691 | B1127: 45230 | C1127: CUST1391 | D1127: PROD6 | E1127: STORE17 | F1127: 1 | G1127: 631 | H1127: 0.04 | I1127: Credit Card | J1127: 605.76 | K1127: =IF(ISBLANK(F1127),J1127/(G1127*(1-H1127)),F1127) -> 1 | L1127: =IF(ISBLANK(G1127),J1127/(F1127*(1-H1127)),G1127) -> 631 | M1127: =IF(ISBLANK(H1127),1-(J1127/(L1127*F1127)),H1127) -> 0.04 | N1127: =IF(ISBLANK(J1127),F1127*G1127*(1-H1127),J1127) -> 605.76
A1128: SALE19 | B1128: 45369 | C1128: CUST1239 | D1128: PROD60 | E1128: STORE13 | F1128: 4 | H1128: 0.04 | I1128: COD | J1128: 1782.4512 | K1128: =IF(ISBLANK(F1128),J1128/(G1128*(1-H1128)),F1128) -> 4 | L1128: =IF(ISBLANK(G1128),J1128/(F1128*(1-H1128)),G1128) -> 464.18 | M1128: =IF(ISBLANK(H1128),1-(J1128/(L1128*F1128)),H1128) -> 0.04 | N1128: =IF(ISBLANK(J1128),F1128*G1128*(1-H1128),J1128) -> 1782.4512
A1129: SALE70 | B1129: 45849 | C1129: CUST1058 | D1129: PROD60 | E1129: STORE5 | F1129: 3 | G1129: 92.24 | H1129: 0.28 | I1129: COD | J1129: 199.2384 | K1129: =IF(ISBLANK(F1129),J1129/(G1129*(1-H1129)),F1129) -> 3 | L1129: =IF(ISBLANK(G1129),J1129/(F1129*(1-H1129)),G1129) -> 92.24 | M1129: =IF(ISBLANK(H1129),1-(J1129/(L1129*F1129)),H1129) -> 0.28 | N1129: =IF(ISBLANK(J1129),F1129*G1129*(1-H1129),J1129) -> 199.2384
A1130: SALE195 | B1130: 45290 | C1130: CUST1427 | D1130: PROD60 | E1130: STORE17 | F1130: 1 | G1130: 889.19 | H1130: 0.03 | I1130: Credit Card | J1130: 862.5143 | K1130: =IF(ISBLANK(F1130),J1130/(G1130*(1-H1130)),F1130) -> 1 | L1130: =IF(ISBLANK(G1130),J1130/(F1130*(1-H1130)),G1130) -> 889.19 | M1130: =IF(ISBLANK(H1130),1-(J1130/(L1130*F1130)),H1130) -> 0.03 | N1130: =IF(ISBLANK(J1130),F1130*G1130*(1-H1130),J1130) -> 862.5143
A1131: SALE229 | B1131: 45348 | C1131: CUST1142 | D1131: PROD60 | E1131: STORE14 | F1131: 3 | G1131: 769.56 | H1131: 0.08 | I1131: Credit Card | J1131: 2123.9856 | K1131: =IF(ISBLANK(F1131),J1131/(G1131*(1-H1131)),F1131) -> 3 | L1131: =IF(ISBLANK(G1131),J1131/(F1131*(1-H1131)),G1131) -> 769.56 | M1131: =IF(ISBLANK(H1131),1-(J1131/(L1131*F1131)),H1131) -> 0.08 | N1131: =IF(ISBLANK(J1131),F1131*G1131*(1-H1131),J1131) -> 2123.9856
A1132: SALE358 | B1132: 45413 | C1132: CUST1210 | D1132: PROD60 | E1132: STORE16 | F1132: 4 | G1132: 537.15 | H1132: 0.06 | I1132: COD | J1132: 2019.684 | K1132: =IF(ISBLANK(F1132),J1132/(G1132*(1-H1132)),F1132) -> 4 | L1132: =IF(ISBLANK(G1132),J1132/(F1132*(1-H1132)),G1132) -> 537.15 | M1132: =IF(ISBLANK(H1132),1-(J1132/(L1132*F1132)),H1132) -> 0.06 | N1132: =IF(ISBLANK(J1132),F1132*G1132*(1-H1132),J1132) -> 2019.684
A1133: SALE851 | B1133: 45484 | C1133: CUST1320 | D1133: PROD60 | E1133: STORE10 | F1133: 4 | G1133: 597.8 | H1133: 0.2 | I1133: Credit Card | J1133: 1912.96 | K1133: =IF(ISBLANK(F1133),J1133/(G1133*(1-H1133)),F1133) -> 4 | L1133: =IF(ISBLANK(G1133),J1133/(F1133*(1-H1133)),G1133) -> 597.8 | M1133: =IF(ISBLANK(H1133),1-(J1133/(L1133*F1133)),H1133) -> 0.2 | N1133: =IF(ISBLANK(J1133),F1133*G1133*(1-H1133),J1133) -> 1912.96
A1134: SALE894 | B1134: 45247 | C1134: CUST1489 | D1134: PROD60 | E1134: STORE13 | F1134: 4 | G1134: 106.48 | H1134: 0.1 | I1134: COD | J1134: 383.328 | K1134: =IF(ISBLANK(F1134),J1134/(G1134*(1-H1134)),F1134) -> 4 | L1134: =IF(ISBLANK(G1134),J1134/(F1134*(1-H1134)),G1134) -> 106.48 | M1134: =IF(ISBLANK(H1134),1-(J1134/(L1134*F1134)),H1134) -> 0.1 | N1134: =IF(ISBLANK(J1134),F1134*G1134*(1-H1134),J1134) -> 383.328
A1135: SALE1014 | B1135: 45681 | C1135: CUST1309 | D1135: PROD60 | E1135: STORE13 | F1135: 2 | G1135: 92.64 | H1135: 0.14 | I1135: COD | J1135: 159.3408 | K1135: =IF(ISBLANK(F1135),J1135/(G1135*(1-H1135)),F1135) -> 2 | L1135: =IF(ISBLANK(G1135),J1135/(F1135*(1-H1135)),G1135) -> 92.64 | M1135: =IF(ISBLANK(H1135),1-(J1135/(L1135*F1135)),H1135) -> 0.14 | N1135: =IF(ISBLANK(J1135),F1135*G1135*(1-H1135),J1135) -> 159.3408
A1136: SALE1175 | B1136: 45932 | C1136: CUST1019 | D1136: PROD60 | E1136: STORE1 | F1136: 2 | G1136: 424.54 | H1136: 0.24 | I1136: PayPal | J1136: 645.3008 | K1136: =IF(ISBLANK(F1136),J1136/(G1136*(1-H1136)),F1136) -> 2 | L1136: =IF(ISBLANK(G1136),J1136/(F1136*(1-H1136)),G1136) -> 424.54 | M1136: =IF(ISBLANK(H1136),1-(J1136/(L1136*F1136)),H1136) -> 0.24 | N1136: =IF(ISBLANK(J1136),F1136*G1136*(1-H1136),J1136) -> 645.3008
A1137: SALE1261 | B1137: 45889 | C1137: CUST1155 | D1137: PROD60 | E1137: STORE10 | F1137: 3 | G1137: 118.25 | H1137: 0.26 | I1137: PayPal | J1137: 262.515 | K1137: =IF(ISBLANK(F1137),J1137/(G1137*(1-H1137)),F1137) -> 3 | L1137: =IF(ISBLANK(G1137),J1137/(F1137*(1-H1137)),G1137) -> 118.25 | M1137: =IF(ISBLANK(H1137),1-(J1137/(L1137*F1137)),H1137) -> 0.26 | N1137: =IF(ISBLANK(J1137),F1137*G1137*(1-H1137),J1137) -> 262.515
A1138: SALE1274 | B1138: 45217 | C1138: CUST1198 | D1138: PROD60 | E1138: STORE11 | F1138: 3 | G1138: 257.11 | H1138: 0.26 | I1138: COD | J1138: 570.7842 | K1138: =IF(ISBLANK(F1138),J1138/(G1138*(1-H1138)),F1138) -> 3 | L1138: =IF(ISBLANK(G1138),J1138/(F1138*(1-H1138)),G1138) -> 257.11 | M1138: =IF(ISBLANK(H1138),1-(J1138/(L1138*F1138)),H1138) -> 0.26 | N1138: =IF(ISBLANK(J1138),F1138*G1138*(1-H1138),J1138) -> 570.7842
A1139: SALE1276 | B1139: 45272 | C1139: CUST1122 | D1139: PROD60 | E1139: STORE12 | F1139: 4 | G1139: 755.82 | H1139: 0.22 | I1139: COD | J1139: 2358.1584 | K1139: =IF(ISBLANK(F1139),J1139/(G1139*(1-H1139)),F1139) -> 4 | L1139: =IF(ISBLANK(G1139),J1139/(F1139*(1-H1139)),G1139) -> 755.82 | M1139: =IF(ISBLANK(H1139),1-(J1139/(L1139*F1139)),H1139) -> 0.22 | N1139: =IF(ISBLANK(J1139),F1139*G1139*(1-H1139),J1139) -> 2358.1584
A1140: SALE1295 | B1140: 45313 | C1140: CUST1247 | D1140: PROD60 | E1140: STORE4 | F1140: 3 | G1140: 543.49 | H1140: 0.05 | I1140: PayPal | J1140: 1548.9465 | K1140: =IF(ISBLANK(F1140),J1140/(G1140*(1-H1140)),F1140) -> 3 | L1140: =IF(ISBLANK(G1140),J1140/(F1140*(1-H1140)),G1140) -> 543.49 | M1140: =IF(ISBLANK(H1140),1-(J1140/(L1140*F1140)),H1140) -> 0.05 | N1140: =IF(ISBLANK(J1140),F1140*G1140*(1-H1140),J1140) -> 1548.9465
... A1750: SALE1789 | B1750: 45579 | C1750: CUST1172 | D1750: PROD88 | E1750: STORE3 | F1750: 2 | G1750: 403.91 | H1750: 0.07 | I1750: Credit Card | J1750: 751.2726 | K1750: =IF(ISBLANK(F1750),J1750/(G1750*(1-H1750)),F1750) -> 2 | L1750: =IF(ISBLANK(G1750),J1750/(F1750*(1-H1750)),G1750) -> 403.91 | M1750: =IF(ISBLANK(H1750),1-(J1750/(L1750*F1750)),H1750) -> 0.07 | N1750: =IF(ISBLANK(J1750),F1750*G1750*(1-H1750),J1750) -> 751.2726
A1751: SALE52 | B1751: 45894 | C1751: CUST1148 | D1751: PROD89 | E1751: STORE6 | F1751: 3 | I1751: Credit Card | J1751: 486.0633 | K1751: =IF(ISBLANK(F1751),J1751/(G1751*(1-H1751)),F1751) -> 3 | L1751: =IF(ISBLANK(G1751),J1751/(F1751*(1-H1751)),G1751) -> 162.0211 | M1751: =IF(ISBLANK(H1751),1-(J1751/(L1751*F1751)),H1751) -> 0 | N1751: =IF(ISBLANK(J1751),F1751*G1751*(1-H1751),J1751) -> 486.0633
A1752: SALE59 | B1752: 45257 | C1752: CUST1367 | D1752: PROD89 | E1752: STORE11 | F1752: 1 | G1752: 996.33 | H1752: 0.23 | I1752: PayPal | J1752: 767.1741 | K1752: =IF(ISBLANK(F1752),J1752/(G1752*(1-H1752)),F1752) -> 1 | L1752: =IF(ISBLANK(G1752),J1752/(F1752*(1-H1752)),G1752) -> 996.33 | M1752: =IF(ISBLANK(H1752),1-(J1752/(L1752*F1752)),H1752) -> 0.23 | N1752: =IF(ISBLANK(J1752),F1752*G1752*(1-H1752),J1752) -> 767.1741
A1753: SALE63 | B1753: 45927 | C1753: CUST1126 | D1753: PROD89 | E1753: STORE12 | F1753: 2 | G1753: 121.37 | H1753: 0.05 | I1753: Credit Card | J1753: 230.603 | K1753: =IF(ISBLANK(F1753),J1753/(G1753*(1-H1753)),F1753) -> 2 | L1753: =IF(ISBLANK(G1753),J1753/(F1753*(1-H1753)),G1753) -> 121.37 | M1753: =IF(ISBLANK(H1753),1-(J1753/(L1753*F1753)),H1753) -> 0.05 | N1753: =IF(ISBLANK(J1753),F1753*G1753*(1-H1753),J1753) -> 230.603
A1754: SALE159 | B1754: 45454 | C1754: CUST1394 | D1754: PROD89 | E1754: STORE16 | F1754: 2 | G1754: 122.23 | H1754: 0.21 | I1754: COD | J1754: 193.1234 | K1754: =IF(ISBLANK(F1754),J1754/(G1754*(1-H1754)),F1754) -> 2 | L1754: =IF(ISBLANK(G1754),J1754/(F1754*(1-H1754)),G1754) -> 122.23 | M1754: =IF(ISBLANK(H1754),1-(J1754/(L1754*F1754)),H1754) -> 0.21 | N1754: =IF(ISBLANK(J1754),F1754*G1754*(1-H1754),J1754) -> 193.1234
A1755: SALE172 | B1755: 45267 | C1755: CUST1344 | D1755: PROD89 | E1755: STORE10 | F1755: 2 | G1755: 827.92 | H1755: 0.25 | I1755: COD | J1755: 1241.88 | K1755: =IF(ISBLANK(F1755),J1755/(G1755*(1-H1755)),F1755) -> 2 | L1755: =IF(ISBLANK(G1755),J1755/(F1755*(1-H1755)),G1755) -> 827.92 | M1755: =IF(ISBLANK(H1755),1-(J1755/(L1755*F1755)),H1755) -> 0.25 | N1755: =IF(ISBLANK(J1755),F1755*G1755*(1-H1755),J1755) -> 1241.88
A1756: SALE184 | B1756: 45686 | C1756: CUST1489 | D1756: PROD89 | E1756: STORE3 | F1756: 1 | G1756: 789.35 | H1756: 0.14 | I1756: PayPal | J1756: 678.841 | K1756: =IF(ISBLANK(F1756),J1756/(G1756*(1-H1756)),F1756) -> 1 | L1756: =IF(ISBLANK(G1756),J1756/(F1756*(1-H1756)),G1756) -> 789.35 | M1756: =IF(ISBLANK(H1756),1-(J1756/(L1756*F1756)),H1756) -> 0.14 | N1756: =IF(ISBLANK(J1756),F1756*G1756*(1-H1756),J1756) -> 678.841
A1757: SALE260 | B1757: 45497 | C1757: CUST1103 | D1757: PROD89 | E1757: STORE19 | F1757: 4 | G1757: 611.3 | H1757: 0.11 | I1757: PayPal | J1757: 2176.228 | K1757: =IF(ISBLANK(F1757),J1757/(G1757*(1-H1757)),F1757) -> 4 | L1757: =IF(ISBLANK(G1757),J1757/(F1757*(1-H1757)),G1757) -> 611.3 | M1757: =IF(ISBLANK(H1757),1-(J1757/(L1757*F1757)),H1757) -> 0.11 | N1757: =IF(ISBLANK(J1757),F1757*G1757*(1-H1757),J1757) -> 2176.228
A1758: SALE270 | B1758: 45735 | C1758: CUST1101 | D1758: PROD89 | E1758: STORE12 | F1758: 4 | G1758: 461.83 | H1758: 0.28 | I1758: PayPal | J1758: 1330.0704 | K1758: =IF(ISBLANK(F1758),J1758/(G1758*(1-H1758)),F1758) -> 4 | L1758: =IF(ISBLANK(G1758),J1758/(F1758*(1-H1758)),G1758) -> 461.83 | M1758: =IF(ISBLANK(H1758),1-(J1758/(L1758*F1758)),H1758) -> 0.28 | N1758: =IF(ISBLANK(J1758),F1758*G1758*(1-H1758),J1758) -> 1330.0704
A1759: SALE381 | B1759: 45427 | C1759: CUST1075 | D1759: PROD89 | E1759: STORE10 | F1759: 3 | G1759: 437.96 | H1759: 0.27 | I1759: COD | J1759: 959.1324 | K1759: =IF(ISBLANK(F1759),J1759/(G1759*(1-H1759)),F1759) -> 3 | L1759: =IF(ISBLANK(G1759),J1759/(F1759*(1-H1759)),G1759) -> 437.96 | M1759: =IF(ISBLANK(H1759),1-(J1759/(L1759*F1759)),H1759) -> 0.27 | N1759: =IF(ISBLANK(J1759),F1759*G1759*(1-H1759),J1759) -> 959.1324
A1760: SALE490 | B1760: 45371 | C1760: CUST1418 | D1760: PROD89 | E1760: STORE18 | F1760: 1 | G1760: 170.43 | H1760: 0.03 | I1760: Credit Card | J1760: 165.3171 | K1760: =IF(ISBLANK(F1760),J1760/(G1760*(1-H1760)),F1760) -> 1 | L1760: =IF(ISBLANK(G1760),J1760/(F1760*(1-H1760)),G1760) -> 170.43 | M1760: =IF(ISBLANK(H1760),1-(J1760/(L1760*F1760)),H1760) -> 0.03 | N1760: =IF(ISBLANK(J1760),F1760*G1760*(1-H1760),J1760) -> 165.3171
A1761: SALE506 | B1761: 45772 | C1761: CUST1042 | D1761: PROD89 | E1761: STORE2 | F1761: 3 | G1761: 21.59 | H1761: 0.16 | I1761: COD | J1761: 54.4068 | K1761: =IF(ISBLANK(F1761),J1761/(G1761*(1-H1761)),F1761) -> 3 | L1761: =IF(ISBLANK(G1761),J1761/(F1761*(1-H1761)),G1761) -> 21.59 | M1761: =IF(ISBLANK(H1761),1-(J1761/(L1761*F1761)),H1761) -> 0.16 | N1761: =IF(ISBLANK(J1761),F1761*G1761*(1-H1761),J1761) -> 54.4068
A1762: SALE780 | B1762: 45477 | C1762: CUST1496 | D1762: PROD89 | E1762: STORE14 | F1762: 4 | G1762: 79.75 | H1762: 0.18 | I1762: PayPal | J1762: 261.58 | K1762: =IF(ISBLANK(F1762),J1762/(G1762*(1-H1762)),F1762) -> 4 | L1762: =IF(ISBLANK(G1762),J1762/(F1762*(1-H1762)),G1762) -> 79.75 | M1762: =IF(ISBLANK(H1762),1-(J1762/(L1762*F1762)),H1762) -> 0.18 | N1762: =IF(ISBLANK(J1762),F1762*G1762*(1-H1762),J1762) -> 261.58
A1763: SALE1071 | B1763: 45215 | C1763: CUST1225 | D1763: PROD89 | E1763: STORE2 | F1763: 4 | G1763: 753.83 | H1763: 0.24 | I1763: Credit Card | J1763: 2291.6432 | K1763: =IF(ISBLANK(F1763),J1763/(G1763*(1-H1763)),F1763) -> 4 | L1763: =IF(ISBLANK(G1763),J1763/(F1763*(1-H1763)),G1763) -> 753.83 | M1763: =IF(ISBLANK(H1763),1-(J1763/(L1763*F1763)),H1763) -> 0.24 | N1763: =IF(ISBLANK(J1763),F1763*G1763*(1-H1763),J1763) -> 2291.6432
... A1797: SALE219 | B1797: 45225 | C1797: CUST1203 | D1797: PROD90 | E1797: STORE15 | F1797: 4 | G1797: 75.37 | H1797: 0.02 | I1797: COD | J1797: 295.4504 | K1797: =IF(ISBLANK(F1797),J1797/(G1797*(1-H1797)),F1797) -> 4 | L1797: =IF(ISBLANK(G1797),J1797/(F1797*(1-H1797)),G1797) -> 75.37 | M1797: =IF(ISBLANK(H1797),1-(J1797/(L1797*F1797)),H1797) -> 0.02 | N1797: =IF(ISBLANK(J1797),F1797*G1797*(1-H1797),J1797) -> 295.4504
A1798: SALE268 | B1798: 45555 | C1798: CUST1406 | D1798: PROD90 | E1798: STORE18 | F1798: 3 | H1798: 0.06 | I1798: Credit Card | J1798: 315.2478 | K1798: =IF(ISBLANK(F1798),J1798/(G1798*(1-H1798)),F1798) -> 3 | L1798: =IF(ISBLANK(G1798),J1798/(F1798*(1-H1798)),G1798) -> 111.79 | M1798: =IF(ISBLANK(H1798),1-(J1798/(L1798*F1798)),H1798) -> 0.06 | N1798: =IF(ISBLANK(J1798),F1798*G1798*(1-H1798),J1798) -> 315.2478
A1799: SALE298 | B1799: 45583 | C1799: CUST1065 | D1799: PROD90 | E1799: STORE1 | F1799: 4 | G1799: 61.98 | H1799: 0.16 | I1799: Credit Card | J1799: 208.2528 | K1799: =IF(ISBLANK(F1799),J1799/(G1799*(1-H1799)),F1799) -> 4 | L1799: =IF(ISBLANK(G1799),J1799/(F1799*(1-H1799)),G1799) -> 61.98 | M1799: =IF(ISBLANK(H1799),1-(J1799/(L1799*F1799)),H1799) -> 0.16 | N1799: =IF(ISBLANK(J1799),F1799*G1799*(1-H1799),J1799) -> 208.2528
A1800: SALE307 | B1800: 45842 | C1800: CUST1451 | D1800: PROD90 | E1800: STORE1 | F1800: 3 | G1800: 135.94 | H1800: 0.2 | I1800: Credit Card | J1800: 326.256 | K1800: =IF(ISBLANK(F1800),J1800/(G1800*(1-H1800)),F1800) -> 3 | L1800: =IF(ISBLANK(G1800),J1800/(F1800*(1-H1800)),G1800) -> 135.94 | M1800: =IF(ISBLANK(H1800),1-(J1800/(L1800*F1800)),H1800) -> 0.2 | N1800: =IF(ISBLANK(J1800),F1800*G1800*(1-H1800),J1800) -> 326.256
A1801: SALE371 | B1801: 45520 | C1801: CUST1231 | D1801: PROD90 | E1801: STORE13 | F1801: 1 | G1801: 752.45 | H1801: 0.21 | I1801: COD | J1801: 594.4355 | K1801: =IF(ISBLANK(F1801),J1801/(G1801*(1-H1801)),F1801) -> 1 | L1801: =IF(ISBLANK(G1801),J1801/(F1801*(1-H1801)),G1801) -> 752.45 | M1801: =IF(ISBLANK(H1801),1-(J1801/(L1801*F1801)),H1801) -> 0.21 | N1801: =IF(ISBLANK(J1801),F1801*G1801*(1-H1801),J1801) -> 594.4355
A1802: SALE565 | B1802: 45843 | C1802: CUST1149 | D1802: PROD90 | E1802: STORE12 | F1802: 1 | G1802: 780.16 | H1802: 0.02 | I1802: COD | J1802: 764.5568 | K1802: =IF(ISBLANK(F1802),J1802/(G1802*(1-H1802)),F1802) -> 1 | L1802: =IF(ISBLANK(G1802),J1802/(F1802*(1-H1802)),G1802) -> 780.16 | M1802: =IF(ISBLANK(H1802),1-(J1802/(L1802*F1802)),H1802) -> 0.02 | N1802: =IF(ISBLANK(J1802),F1802*G1802*(1-H1802),J1802) -> 764.5568
A1803: SALE622 | B1803: 45421 | C1803: CUST1036 | D1803: PROD90 | E1803: STORE5 | F1803: 2 | G1803: 678.98 | H1803: 0.23 | I1803: Credit Card | J1803: 1045.6292 | K1803: =IF(ISBLANK(F1803),J1803/(G1803*(1-H1803)),F1803) -> 2 | L1803: =IF(ISBLANK(G1803),J1803/(F1803*(1-H1803)),G1803) -> 678.98 | M1803: =IF(ISBLANK(H1803),1-(J1803/(L1803*F1803)),H1803) -> 0.23 | N1803: =IF(ISBLANK(J1803),F1803*G1803*(1-H1803),J1803) -> 1045.6292
A1804: SALE642 | B1804: 45711 | C1804: CUST1146 | D1804: PROD90 | E1804: STORE1 | F1804: 3 | G1804: 853.32 | H1804: 0.07 | I1804: COD | J1804: 2380.7628 | K1804: =IF(ISBLANK(F1804),J1804/(G1804*(1-H1804)),F1804) -> 3 | L1804: =IF(ISBLANK(G1804),J1804/(F1804*(1-H1804)),G1804) -> 853.32 | M1804: =IF(ISBLANK(H1804),1-(J1804/(L1804*F1804)),H1804) -> 0.07 | N1804: =IF(ISBLANK(J1804),F1804*G1804*(1-H1804),J1804) -> 2380.7628
A1805: SALE660 | B1805: 45914 | C1805: CUST1180 | D1805: PROD90 | E1805: STORE18 | F1805: 3 | G1805: 107.44 | H1805: 0.27 | I1805: PayPal | J1805: 235.2936 | K1805: =IF(ISBLANK(F1805),J1805/(G1805*(1-H1805)),F1805) -> 3 | L1805: =IF(ISBLANK(G1805),J1805/(F1805*(1-H1805)),G1805) -> 107.44 | M1805: =IF(ISBLANK(H1805),1-(J1805/(L1805*F1805)),H1805) -> 0.27 | N1805: =IF(ISBLANK(J1805),F1805*G1805*(1-H1805),J1805) -> 235.2936
A1806: SALE702 | B1806: 45459 | C1806: CUST1221 | D1806: PROD90 | E1806: STORE4 | F1806: 1 | G1806: 900.94 | H1806: 0.1 | I1806: Credit Card | J1806: 810.846 | K1806: =IF(ISBLANK(F1806),J1806/(G1806*(1-H1806)),F1806) -> 1 | L1806: =IF(ISBLANK(G1806),J1806/(F1806*(1-H1806)),G1806) -> 900.94 | M1806: =IF(ISBLANK(H1806),1-(J1806/(L1806*F1806)),H1806) -> 0.1 | N1806: =IF(ISBLANK(J1806),F1806*G1806*(1-H1806),J1806) -> 810.846
A1807: SALE960 | B1807: 45227 | C1807: CUST1007 | D1807: PROD90 | E1807: STORE7 | F1807: 1 | G1807: 537.26 | H1807: 0.09 | I1807: Credit Card | J1807: 488.9066 | K1807: =IF(ISBLANK(F1807),J1807/(G1807*(1-H1807)),F1807) -> 1 | L1807: =IF(ISBLANK(G1807),J1807/(F1807*(1-H1807)),G1807) -> 537.26 | M1807: =IF(ISBLANK(H1807),1-(J1807/(L1807*F1807)),H1807) -> 0.09 | N1807: =IF(ISBLANK(J1807),F1807*G1807*(1-H1807),J1807) -> 488.9066
A1808: SALE1159 | B1808: 45881 | C1808: CUST1346 | D1808: PROD90 | E1808: STORE16 | F1808: 1 | G1808: 269.25 | H1808: 0.14 | I1808: PayPal | J1808: 231.555 | K1808: =IF(ISBLANK(F1808),J1808/(G1808*(1-H1808)),F1808) -> 1 | L1808: =IF(ISBLANK(G1808),J1808/(F1808*(1-H1808)),G1808) -> 269.25 | M1808: =IF(ISBLANK(H1808),1-(J1808/(L1808*F1808)),H1808) -> 0.14 | N1808: =IF(ISBLANK(J1808),F1808*G1808*(1-H1808),J1808) -> 231.555
A1809: SALE1237 | B1809: 45912 | C1809: CUST1134 | D1809: PROD90 | E1809: STORE13 | F1809: 1 | G1809: 822.6 | H1809: 0.29 | I1809: PayPal | J1809: 584.046 | K1809: =IF(ISBLANK(F1809),J1809/(G1809*(1-H1809)),F1809) -> 1 | L1809: =IF(ISBLANK(G1809),J1809/(F1809*(1-H1809)),G1809) -> 822.6 | M1809: =IF(ISBLANK(H1809),1-(J1809/(L1809*F1809)),H1809) -> 0.29 | N1809: =IF(ISBLANK(J1809),F1809*G1809*(1-H1809),J1809) -> 584.046
A1810: SALE1395 | B1810: 45343 | C1810: CUST1278 | D1810: PROD90 | E1810: STORE11 | F1810: 1 | G1810: 413.65 | H1810: 0.1 | I1810: COD | J1810: 372.285 | K1810: =IF(ISBLANK(F1810),J1810/(G1810*(1-H1810)),F1810) -> 1 | L1810: =IF(ISBLANK(G1810),J1810/(F1810*(1-H1810)),G1810) -> 413.65 | M1810: =IF(ISBLANK(H1810),1-(J1810/(L1810*F1810)),H1810) -> 0.1 | N1810: =IF(ISBLANK(J1810),F1810*G1810*(1-H1810),J1810) -> 372.285
... A1960: SALE1751 | B1960: 45296 | C1960: CUST1257 | D1960: PROD97 | E1960: STORE19 | F1960: 4 | G1960: 715.42 | H1960: 0.29 | I1960: PayPal | J1960: 2031.7928 | K1960: =IF(ISBLANK(F1960),J1960/(G1960*(1-H1960)),F1960) -> 4 | L1960: =IF(ISBLANK(G1960),J1960/(F1960*(1-H1960)),G1960) -> 715.42 | M1960: =IF(ISBLANK(H1960),1-(J1960/(L1960*F1960)),H1960) -> 0.29 | N1960: =IF(ISBLANK(J1960),F1960*G1960*(1-H1960),J1960) -> 2031.7928
A1961: SALE26 | B1961: 45294 | C1961: CUST1213 | D1961: PROD98 | E1961: STORE8 | F1961: 4 | G1961: 156.16 | I1961: Credit Card | J1961: 599.6544 | K1961: =IF(ISBLANK(F1961),J1961/(G1961*(1-H1961)),F1961) -> 4 | L1961: =IF(ISBLANK(G1961),J1961/(F1961*(1-H1961)),G1961) -> 156.16 | M1961: =IF(ISBLANK(H1961),1-(J1961/(L1961*F1961)),H1961) -> 0.04 | N1961: =IF(ISBLANK(J1961),F1961*G1961*(1-H1961),J1961) -> 599.6544
A1962: SALE252 | B1962: 45925 | C1962: CUST1449 | D1962: PROD98 | E1962: STORE19 | F1962: 1 | G1962: 549.52 | H1962: 0.1 | I1962: PayPal | J1962: 494.568 | K1962: =IF(ISBLANK(F1962),J1962/(G1962*(1-H1962)),F1962) -> 1 | L1962: =IF(ISBLANK(G1962),J1962/(F1962*(1-H1962)),G1962) -> 549.52 | M1962: =IF(ISBLANK(H1962),1-(J1962/(L1962*F1962)),H1962) -> 0.1 | N1962: =IF(ISBLANK(J1962),F1962*G1962*(1-H1962),J1962) -> 494.568
...

Sheet Customer_Loyalty level
A1: Row Labels | B1: Average of Total_Amount | C1: Sum of Total_Amount | D1: Sum of Quantity | E1: Max of Discount | F1: Max of Order_Date | G1: Loyalty_Level
A2: CUST1219 | B2: 1714.7713 | C2: 17147.713 | D2: 29 | E2: 0.24 | F2: 45854 | G2: =VLOOKUP(A2,Customer_Dim!$A$1:$H$501,8,0) -> Gold
A3: CUST1084 | B3: 1934.6377 | C3: 15477.101 | D3: 27 | E3: 0.29 | F3: 45906 | G3: =VLOOKUP(A3,Customer_Dim!$A$1:$H$501,8,0) -> Platinum
A4: CUST1057 | B4: 1850.4244 | C4: 14803.395 | D4: 24 | E4: 0.27 | F4: 45859 | G4: =VLOOKUP(A4,Customer_Dim!$A$1:$H$501,8,0) -> Platinum
A5: CUST1319 | B5: 1945.7693 | C5: 13620.385 | D5: 17 | E5: 0.19 | F5: 45579 | G5: =VLOOKUP(A5,Customer_Dim!$A$1:$H$501,8,0) -> Platinum
A6: CUST1067 | B6: 1361.0902 | C6: 13610.902 | D6: 23 | E6: 0.3 | F6: 45873 | G6: =VLOOKUP(A6,Customer_Dim!$A$1:$H$501,8,0) -> Silver
A7: CUST1168 | B7: 1467.6159 | C7: 13208.543 | D7: 25 | E7: 0.28 | F7: 45929 | G7: =VLOOKUP(A7,Customer_Dim!$A$1:$H$501,8,0) -> Platinum
A8: CUST1013 | B8: 1857.9667 | C8: 13005.767 | D8: 24 | E8: 0.22 | F8: 45764 | G8: =VLOOKUP(A8,Customer_Dim!$A$1:$H$501,8,0) -> Silver
A9: CUST1485 | B9: 1808.1438 | C9: 12657.007 | D9: 22 | E9: 0.3 | F9: 45864 | G9: =VLOOKUP(A9,Customer_Dim!$A$1:$H$501,8,0) -> Bronze
A10: CUST1470 | B10: 1712.3642 | C10: 11986.55 | D10: 25 | E10: 0.3 | F10: 45921 | G10: =VLOOKUP(A10,Customer_Dim!$A$1:$H$501,8,0) -> Gold
A11: CUST1054 | B11: 1315.2058 | C11: 11836.852 | D11: 30 | E11: 0.25 | F11: 45862 | G11: =VLOOKUP(A11,Customer_Dim!$A$1:$H$501,8,0) -> Platinum
A12: CUST1051 | B12: 1467.7466 | C12: 11741.973 | D12: 25 | E12: 0.3 | F12: 45886 | G12: =VLOOKUP(A12,Customer_Dim!$A$1:$H$501,8,0) -> Gold
A13: CUST1161 | B13: 1637.1794 | C13: 11460.256 | D13: 18 | E13: 0.24 | F13: 45773 | G13: =VLOOKUP(A13,Customer_Dim!$A$1:$H$501,8,0) -> Silver
... A493: CUST1340 | B493: 36.0272 | C493: 36.0272 | D493: 2 | E493: 0.12 | F493: 45556 | G493: =VLOOKUP(A493,Customer_Dim!$A$1:$H$501,8,0) -> Bronze
A494: Grand Total | B494: 1087.1973 | C494: 2174394.7 | D494: 4964 | E494: 0.3 | F494: 45943

Sheet Ref sheet
A1: Product_ID | B1: Store_ID | C1: Quantity | D1: Unit_Price | E1: Discount | F1: Payment_Type | G1: Total_Amount Imputed
A2: PROD97 | B2: STORE3 | C2: 1 | D2: 218.04 | E2: 0.09 | F2: Credit Card | G2: 198.4164
A3: PROD74 | B3: STORE17 | C3: 3 | D3: 104.47 | E3: 0.27 | F3: PayPal | G3: 228.7893
A4: PROD49 | B4: STORE8 | C4: 4 | D4: 914.05 | E4: 0.25 | F4: Credit Card | G4: 2742.15
A5: PROD76 | B5: STORE8 | C5: 1 | D5: 921.51 | E5: 0.16 | F5: COD | G5: 774.0684
A6: PROD59 | B6: STORE5 | C6: 3 | D6: 745.3 | E6: 0.18 | F6: Credit Card | G6: 1833.438
A7: PROD15 | B7: STORE7 | C7: 3 | D7: 147.01 | E7: 0.19 | F7: COD | G7: 357.2343
A8: PROD56 | B8: STORE4 | C8: 2 | D8: 785.31 | E8: 0.15 | F8: PayPal | G8: 1335.027
A9: PROD70 | B9: STORE8 | C9: 4 | D9: 342.39 | E9: 0.23 | F9: PayPal | G9: 1054.5612
A10: PROD99 | B10: STORE5 | C10: 3 | D10: 448.25 | E10: 0.07 | F10: PayPal | G10: 1250.6175
A11: PROD33 | B11: STORE0 | C11: 2 | D11: 873.17 | E11: 0.23 | F11: PayPal | G11: 1344.6818
A12: PROD24 | B12: STORE14 | C12: 1 | D12: 278.63 | E12: 0.07 | F12: Credit Card | G12: 259.1259
A13: PROD39 | B13: STORE1 | C13: 4 | D13: 286.92 | E13: 0.17 | F13: Credit Card | G13: 952.5744
... A20: PROD39 | B20: STORE4 | C20: 2 | D20: 559.23 | E20: 0.25 | F20: COD | G20: 838.845
A21: PROD60 | B21: STORE13 | C21: 4 | E21: 0.04 | F21: COD | G21: 1782.4512
A22: PROD72 | B22: STORE17 | C22: 3 | D22: 986.04 | E22: 0.27 | F22: COD | G22: 2159.4276
A23: PROD43 | B23: STORE18 | C23: 1 | D23: 589.56 | E23: 0.22 | F23: Credit Card | G23: 459.8568
A24: PROD69 | B24: STORE10 | C24: 3 | D24: 979.42 | E24: 0.03 | F24: PayPal | G24: 2850.1122
A25: PROD12 | B25: STORE8 | C25: 1 | D25: 719.28 | E25: 0.08 | F25: Credit Card | G25: 661.7376
A26: PROD67 | B26: STORE6 | C26: 3 | D26: 77.6 | E26: 0.07 | F26: Credit Card | G26: 216.504
A27: PROD5 | B27: STORE3 | C27: 4 | D27: 852.71 | E27: 0.14 | F27: PayPal | G27: 2933.3224
A28: PROD98 | B28: STORE8 | C28: 4 | D28: 156.16 | F28: Credit Card | G28: 599.6544
A29: PROD77 | B29: STORE8 | C29: 3 | D29: 815.49 | E29: 0.17 | F29: Credit Card | G29: 2030.5701
A30: PROD13 | B30: STORE2 | C30: 2 | D30: 74.21 | E30: 0.11 | F30: PayPal | G30: 132.0938
A31: PROD99 | B31: STORE3 | C31: 4 | D31: 451.67 | E31: 0.15 | F31: Credit Card | G31: 1535.678
A32: PROD5 | B32: STORE19 | C32: 1 | D32: 429.38 | E32: 0.13 | F32: PayPal | G32: 373.5606
A33: PROD53 | B33: STORE12 | C33: 2 | D33: 148.96 | E33: 0.03 | F33: COD | G33: 288.9824
A34: PROD75 | B34: STORE8 | C34: 4 | D34: 313.83 | E34: 0.08 | F34: Credit Card | G34: 1154.8944
A35: PROD12 | B35: STORE6 | C35: 2 | D35: 717.31 | E35: 0.15 | F35: Credit Card | G35: 1219.427
A36: PROD79 | B36: STORE1 | C36: 3 | D36: 873.22 | E36: 0.18 | F36: Credit Card | G36: 2148.1212
A37: PROD16 | B37: STORE3 | C37: 4 | D37: 109.36 | E37: 0.19 | F37: COD | G37: 354.3264
A38: PROD5 | B38: STORE7 | C38: 3 | D38: 559.52 | E38: 0.16 | F38: PayPal | G38: 1409.9904
A39: PROD10 | B39: STORE17 | C39: 3 | D39: 121.76 | E39: 0.27 | F39: PayPal | G39: 266.6544
A40: PROD33 | B40: STORE13 | C40: 4 | D40: 735.32 | E40: 0.06 | F40: COD | G40: 2764.8032
... A53: PROD69 | B53: STORE7 | C53: 3 | D53: 76.57 | E53: 0.26 | F53: Credit Card | G53: 169.9854
A54: PROD89 | B54: STORE6 | C54: 3 | F54: Credit Card | G54: 486.0633
A55: PROD20 | B55: STORE8 | C55: 1 | D55: 900.35 | E55: 0.13 | F55: COD | G55: 783.3045
A56: PROD40 | B56: STORE10 | C56: 4 | D56: 428.09 | E56: 0.07 | F56: Credit Card | G56: 1592.4948
A57: PROD49 | B57: STORE11 | C57: 2 | D57: 559.71 | E57: 0.3 | F57: COD | G57: 783.594
A58: PROD34 | B58: STORE6 | C58: 2 | D58: 833.7 | E58: 0.06 | F58: PayPal | G58: 1567.356
A59: PROD47 | B59: STORE14 | C59: 2 | D59: 680.16 | E59: 0.28 | F59: Credit Card | G59: 979.4304
A60: PROD15 | B60: STORE7 | C60: 4 | D60: 733.42 | F60: PayPal | G60: 2552.3016
A61: PROD89 | B61: STORE11 | C61: 1 | D61: 996.33 | E61: 0.23 | F61: PayPal | G61: 767.1741
A62: PROD31 | B62: STORE10 | C62: 1 | D62: 198.83 | E62: 0.09 | F62: COD | G62: 180.9353
A63: PROD19 | B63: STORE7 | C63: 1 | D63: 374.92 | E63: 0.18 | F63: PayPal | G63: 307.4344
A64: PROD93 | B64: STORE16 | C64: 1 | D64: 468.94 | E64: 0.12 | F64: Credit Card | G64: 412.6672
A65: PROD89 | B65: STORE12 | C65: 2 | D65: 121.37 | E65: 0.05 | F65: Credit Card | G65: 230.603
A66: PROD53 | B66: STORE10 | C66: 3 | D66: 480.06 | E66: 0.01 | F66: Credit Card | G66: 1425.7782
A67: PROD99 | B67: STORE17 | C67: 2 | D67: 856.57 | E67: 0.24 | F67: Credit Card | G67: 1301.9864
A68: PROD77 | B68: STORE2 | C68: 4 | D68: 814.25 | E68: 0.18 | F68: Credit Card | G68: 2670.74
A69: PROD12 | B69: STORE2 | C69: 1 | D69: 989.17 | E69: 0.2 | F69: PayPal | G69: 791.336
A70: PROD72 | B70: STORE10 | C70: 4 | D70: 62.48 | E70: 0.18 | F70: Credit Card | G70: 204.9344
A71: PROD13 | B71: STORE16 | C71: 4 | D71: 561.24 | E71: 0.24 | F71: Credit Card | G71: 1706.1696
A72: PROD60 | B72: STORE5 | C72: 3 | D72: 92.24 | E72: 0.28 | F72: COD | G72: 199.2384
... A260: PROD35 | B260: STORE17 | C260: 1 | D260: 222.94 | E260: 0.19 | F260: Credit Card | G260: 180.5814
A261: PROD35 | B261: STORE2 | C261: 2 | D261: 355.3 | F261: PayPal | G261: 589.798
A262: PROD89 | B262: STORE19 | C262: 4 | D262: 611.3 | E262: 0.11 | F262: PayPal | G262: 2176.228
A263: PROD0 | B263: STORE8 | C263: 4 | D263: 849.21 | E263: 0.07 | F263: Credit Card | G263: 3159.0612
A264: PROD42 | B264: STORE7 | C264: 3 | D264: 553.12 | E264: 0.28 | F264: COD | G264: 1194.7392
A265: PROD91 | B265: STORE9 | C265: 2 | D265: 903.08 | E265: 0.18 | F265: COD | G265: 1481.0512
A266: PROD16 | B266: STORE11 | C266: 4 | D266: 640.23 | E266: 0.06 | F266: COD | G266: 2407.2648
A267: PROD21 | B267: STORE6 | C267: 1 | D267: 518 | E267: 0.25 | F267: Credit Card | G267: 388.5
A268: PROD64 | B268: STORE4 | C268: 4 | D268: 779.25 | E268: 0.25 | F268: Credit Card | G268: 2337.75
A269: PROD83 | B269: STORE7 | C269: 2 | D269: 467.75 | E269: 0.26 | F269: Credit Card | G269: 692.27
A270: PROD90 | B270: STORE18 | C270: 3 | E270: 0.06 | F270: Credit Card | G270: 315.2478
A271: PROD37 | B271: STORE0 | C271: 4 | D271: 747.01 | E271: 0.13 | F271: PayPal | G271: 2599.5948
A272: PROD89 | B272: STORE12 | C272: 4 | D272: 461.83 | E272: 0.28 | F272: PayPal | G272: 1330.0704
A273: PROD70 | B273: STORE8 | C273: 2 | D273: 105.15 | E273: 0.06 | F273: Credit Card | G273: 197.682
A274: PROD23 | B274: STORE3 | C274: 3 | D274: 610.24 | E274: 0.17 | F274: COD | G274: 1519.4976
A275: PROD74 | B275: STORE8 | C275: 1 | D275: 872.12 | E275: 0.07 | F275: PayPal | G275: 811.0716
A276: PROD10 | B276: STORE1 | C276: 1 | D276: 406.79 | E276: 0.03 | F276: COD | G276: 394.5863
A277: PROD54 | B277: STORE14 | C277: 1 | D277: 606.01 | E277: 0.04 | F277: PayPal | G277: 581.7696
A278: PROD17 | B278: STORE5 | C278: 4 | D278: 322.58 | E278: 0.06 | F278: Credit Card | G278: 1212.9008
A279: PROD77 | B279: STORE18 | C279: 4 | D279: 463.17 | E279: 0.06 | F279: PayPal | G279: 1741.5192
A280: PROD25 | B280: STORE7 | C280: 4 | D280: 285.82 | E280: 0.18 | F280: PayPal | G280: 937.4896
A281: PROD37 | B281: STORE11 | C281: 3 | D281: 995.38 | E281: 0.1 | F281: PayPal | G281: 2687.526
A282: PROD62 | B282: STORE8 | C282: 1 | D282: 329.31 | E282: 0.09 | F282: Credit Card | G282: 299.6721
... A2001: PROD76 | B2001: STORE19 | C2001: 3 | D2001: 68.45 | E2001: 0.17 | F2001: PayPal | G2001: 170.4405

Sheet Mean - Meadian - Mode
A1: Row Labels | B1: Sum of Sum of Total_Amount | C1: Age | D1: Age group | E1: Gender | F1: State | I1: Age | M1: Sales amount
A2: CUST1000 | B2: 2437.6722 | C2: =VLOOKUP(A2,Customer_Dim!$A$2:$H$501,3,0) -> 55 | D2: =IF(C2<20,"Below 20", IF(C2<40,"20–39", IF(C2<60,"40–59","60+"))) -> 40–59 | E2: =VLOOKUP(A2,Customer_Dim!$A$2:$H$501,4,0) -> Male | F2: =VLOOKUP(A2,Customer_Dim!$A$2:$H$501,6,0) -> North Carolina | I2: Mean | J2: =AVERAGE(C2:C493) -> 41.571138 | M2: Mean | N2: =AVERAGE(B2:B494) -> 8821.0738
A3: CUST1001 | B3: 1941.1877 | C3: =VLOOKUP(A3,Customer_Dim!$A$2:$H$501,3,0) -> 26 | D3: =IF(C3<20,"Below 20", IF(C3<40,"20–39", IF(C3<60,"40–59","60+"))) -> 20–39 | E3: =VLOOKUP(A3,Customer_Dim!$A$2:$H$501,4,0) -> Female | F3: =VLOOKUP(A3,Customer_Dim!$A$2:$H$501,6,0) -> North Dakota | I3: Median | J3: =MEDIAN(C2:C492) -> 42 | M3: Median | N3: =MEDIAN(B3:B495) -> 4002.9356
A4: CUST1002 | B4: 2078.4183 | C4: =VLOOKUP(A4,Customer_Dim!$A$2:$H$501,3,0) -> 29 | D4: =IF(C4<20,"Below 20", IF(C4<40,"20–39", IF(C4<60,"40–59","60+"))) -> 20–39 | E4: =VLOOKUP(A4,Customer_Dim!$A$2:$H$501,4,0) -> Female | F4: =VLOOKUP(A4,Customer_Dim!$A$2:$H$501,6,0) -> Alabama | I4: Mode | J4: =MODE(C2:C493) -> 46 | M4: SD | N4: =STDEV(B4:B496) -> 218771.12
A5: CUST1003 | B5: 2330.867 | C5: =VLOOKUP(A5,Customer_Dim!$A$2:$H$501,3,0) -> 59 | D5: =IF(C5<20,"Below 20", IF(C5<40,"20–39", IF(C5<60,"40–59","60+"))) -> 40–59 | E5: =VLOOKUP(A5,Customer_Dim!$A$2:$H$501,4,0) -> Female | F5: =VLOOKUP(A5,Customer_Dim!$A$2:$H$501,6,0) -> Ohio
A6: CUST1004 | B6: 5830.6476 | C6: =VLOOKUP(A6,Customer_Dim!$A$2:$H$501,3,0) -> 64 | D6: =IF(C6<20,"Below 20", IF(C6<40,"20–39", IF(C6<60,"40–59","60+"))) -> 60+ | E6: =VLOOKUP(A6,Customer_Dim!$A$2:$H$501,4,0) -> Female | F6: =VLOOKUP(A6,Customer_Dim!$A$2:$H$501,6,0) -> California
A7: CUST1005 | B7: 4795.0978 | C7: =VLOOKUP(A7,Customer_Dim!$A$2:$H$501,3,0) -> 24 | D7: =IF(C7<20,"Below 20", IF(C7<40,"20–39", IF(C7<60,"40–59","60+"))) -> 20–39 | E7: =VLOOKUP(A7,Customer_Dim!$A$2:$H$501,4,0) -> Male | F7: =VLOOKUP(A7,Customer_Dim!$A$2:$H$501,6,0) -> Oregon
A8: CUST1006 | B8: 6348.0162 | C8: =VLOOKUP(A8,Customer_Dim!$A$2:$H$501,3,0) -> 29 | D8: =IF(C8<20,"Below 20", IF(C8<40,"20–39", IF(C8<60,"40–59","60+"))) -> 20–39 | E8: =VLOOKUP(A8,Customer_Dim!$A$2:$H$501,4,0) -> Female | F8: =VLOOKUP(A8,Customer_Dim!$A$2:$H$501,6,0) -> South Dakota
A9: CUST1007 | B9: 10211.024 | C9: =VLOOKUP(A9,Customer_Dim!$A$2:$H$501,3,0) -> 29 | D9: =IF(C9<20,"Below 20", IF(C9<40,"20–39", IF(C9<60,"40–59","60+"))) -> 20–39 | E9: =VLOOKUP(A9,Customer_Dim!$A$2:$H$501,4,0) -> Female | F9: =VLOOKUP(A9,Customer_Dim!$A$2:$H$501,6,0) -> West Virginia
A10: CUST1008 | B10: 4029.7085 | C10: =VLOOKUP(A10,Customer_Dim!$A$2:$H$501,3,0) -> 53 | D10: =IF(C10<20,"Below 20", IF(C10<40,"20–39", IF(C10<60,"40–59","60+"))) -> 40–59 | E10: =VLOOKUP(A10,Customer_Dim!$A$2:$H$501,4,0) -> Female | F10: =VLOOKUP(A10,Customer_Dim!$A$2:$H$501,6,0) -> New Hampshire
A11: CUST1009 | B11: 3903.6052 | C11: =VLOOKUP(A11,Customer_Dim!$A$2:$H$501,3,0) -> 64 | D11: =IF(C11<20,"Below 20", IF(C11<40,"20–39", IF(C11<60,"40–59","60+"))) -> 60+ | E11: =VLOOKUP(A11,Customer_Dim!$A$2:$H$501,4,0) -> Male | F11: =VLOOKUP(A11,Customer_Dim!$A$2:$H$501,6,0) -> Pennsylvania
A12: CUST1010 | B12: 2235.5459 | C12: =VLOOKUP(A12,Customer_Dim!$A$2:$H$501,3,0) -> 53 | D12: =IF(C12<20,"Below 20", IF(C12<40,"20–39", IF(C12<60,"40–59","60+"))) -> 40–59 | E12: =VLOOKUP(A12,Customer_Dim!$A$2:$H$501,4,0) -> Male | F12: =VLOOKUP(A12,Customer_Dim!$A$2:$H$501,6,0) -> Pennsylvania
A13: CUST1011 | B13: 3868.3903 | C13: =VLOOKUP(A13,Customer_Dim!$A$2:$H$501,3,0) -> 28 | D13: =IF(C13<20,"Below 20", IF(C13<40,"20–39", IF(C13<60,"40–59","60+"))) -> 20–39 | E13: =VLOOKUP(A13,Customer_Dim!$A$2:$H$501,4,0) -> Female | F13: =VLOOKUP(A13,Customer_Dim!$A$2:$H$501,6,0) -> New York
A14: CUST1012 | B14: 7752.779 | C14: =VLOOKUP(A14,Customer_Dim!$A$2:$H$501,3,0) -> 55 | D14: =IF(C14<20,"Below 20", IF(C14<40,"20–39", IF(C14<60,"40–59","60+"))) -> 40–59 | E14: =VLOOKUP(A14,Customer_Dim!$A$2:$H$501,4,0) -> Female | F14: =VLOOKUP(A14,Customer_Dim!$A$2:$H$501,6,0) -> Kansas
A15: CUST1013 | B15: 13005.767 | C15: =VLOOKUP(A15,Customer_Dim!$A$2:$H$501,3,0) -> 32 | D15: =IF(C15<20,"Below 20", IF(C15<40,"20–39", IF(C15<60,"40–59","60+"))) -> 20–39 | E15: =VLOOKUP(A15,Customer_Dim!$A$2:$H$501,4,0) -> Female | F15: =VLOOKUP(A15,Customer_Dim!$A$2:$H$501,6,0) -> Montana
A16: CUST1014 | B16: 2365.2003 | C16: =VLOOKUP(A16,Customer_Dim!$A$2:$H$501,3,0) -> 53 | D16: =IF(C16<20,"Below 20", IF(C16<40,"20–39", IF(C16<60,"40–59","60+"))) -> 40–59 | E16: =VLOOKUP(A16,Customer_Dim!$A$2:$H$501,4,0) -> Female | F16: =VLOOKUP(A16,Customer_Dim!$A$2:$H$501,6,0) -> Nebraska
... A493: CUST1499 | B493: 5661.8447 | C493: =VLOOKUP(A493,Customer_Dim!$A$2:$H$501,3,0) -> 27 | D493: =IF(C493<20,"Below 20", IF(C493<40,"20–39", IF(C493<60,"40–59","60+"))) -> 20–39 | E493: =VLOOKUP(A493,Customer_Dim!$A$2:$H$501,4,0) -> Female | F493: =VLOOKUP(A493,Customer_Dim!$A$2:$H$501,6,0) -> Oregon
A494: Grand Total | B494: 2174394.7
A495: Grand Total | B495: 4348789.4

Sheet Product - Sales
A1: Product ID | B1: Sum of Total_Amount | C1: Sum of Quantity | D1: Product_Name
A2: PROD39 | B2: 41852.503 | C2: 84 | D2: =VLOOKUP(A2,Product_Dim!$A$1:$G$101,2,0) -> Portable Power Bank
A3: PROD73 | B3: 38281.015 | C3: 77 | D3: =VLOOKUP(A3,Product_Dim!$A$1:$G$101,2,0) -> Shin Guards – Adult
A4: PROD37 | B4: 35489.62 | C4: 87 | D4: =VLOOKUP(A4,Product_Dim!$A$1:$G$101,2,0) -> Men's Casual Sneakers
A5: PROD34 | B5: 34699.833 | C5: 84 | D5: =VLOOKUP(A5,Product_Dim!$A$1:$G$101,2,0) -> Gaming Mechanical Keyboard
A6: PROD91 | B6: 33993.659 | C6: 67 | D6: =VLOOKUP(A6,Product_Dim!$A$1:$G$101,2,0) -> Women's High Heels
A7: PROD76 | B7: 33566.8 | C7: 73 | D7: =VLOOKUP(A7,Product_Dim!$A$1:$G$101,2,0) -> Wireless Mouse
A8: PROD31 | B8: 31070.456 | C8: 63 | D8: =VLOOKUP(A8,Product_Dim!$A$1:$G$101,2,0) -> Basketball
A9: PROD59 | B9: 30236.698 | C9: 66 | D9: =VLOOKUP(A9,Product_Dim!$A$1:$G$101,2,0) -> Men's Hair Styling Gel
A10: PROD96 | B10: 28572.692 | C10: 45 | D10: =VLOOKUP(A10,Product_Dim!$A$1:$G$101,2,0) -> Women's Formal Blazer
A11: PROD17 | B11: 28324.049 | C11: 70 | D11: =VLOOKUP(A11,Product_Dim!$A$1:$G$101,2,0) -> Soccer Training Cone Set
A12: PROD15 | B12: 28285.614 | C12: 72 | D12: =VLOOKUP(A12,Product_Dim!$A$1:$G$101,2,0) -> 4K Home Projector
A13: PROD89 | B13: 28237.931 | C13: 68 | D13: =VLOOKUP(A13,Product_Dim!$A$1:$G$101,2,0) -> Face Foundation Kit
... A101: PROD47 | B101: 7948.3905 | C101: 29 | D101: =VLOOKUP(A101,Product_Dim!$A$1:$G$101,2,0) -> Makeup Brush Set
A102: Grand Total | B102: 2174394.7 | C102: 4964

Sheet Store - Sales
A1: Sum of Total_Amount Imputed
A2: Store ID | B2: COD | C2: Credit Card | D2: PayPal | E2: Total sales | F2: Store name
A3: STORE8 | B3: 34142.73 | C3: 72215.371 | D3: 52613.361 | E3: 158971.46 | F3: =VLOOKUP(A3,Store_Dim!$A$1:$E$21,2,0) -> Bean, Jones and Park
A4: STORE3 | B4: 33446.974 | C4: 46541.045 | D4: 45023.81 | E4: 125011.83 | F4: =VLOOKUP(A4,Store_Dim!$A$1:$E$21,2,0) -> Johnson-Wright
A5: STORE17 | B5: 38114.378 | C5: 33813.865 | D5: 50248.304 | E5: 122176.55 | F5: =VLOOKUP(A5,Store_Dim!$A$1:$E$21,2,0) -> Holloway Ltd
A6: STORE4 | B6: 24588.907 | C6: 45275.221 | D6: 48949.988 | E6: 118814.12 | F6: =VLOOKUP(A6,Store_Dim!$A$1:$E$21,2,0) -> Alexander Group
A7: STORE12 | B7: 31116.781 | C7: 53805.05 | D7: 31907.39 | E7: 116829.22 | F7: =VLOOKUP(A7,Store_Dim!$A$1:$E$21,2,0) -> Thomas, Bridges and Harris
A8: STORE6 | B8: 36767.687 | C8: 34688.908 | D8: 43077.202 | E8: 114533.8 | F8: =VLOOKUP(A8,Store_Dim!$A$1:$E$21,2,0) -> Benson-Elliott
A9: STORE13 | B9: 42434.351 | C9: 37172.494 | D9: 34794.627 | E9: 114401.47 | F9: =VLOOKUP(A9,Store_Dim!$A$1:$E$21,2,0) -> Gardner, Humphrey and Contreras
A10: STORE16 | B10: 47433.617 | C10: 33648.204 | D10: 30623.122 | E10: 111704.94 | F10: =VLOOKUP(A10,Store_Dim!$A$1:$E$21,2,0) -> Frederick-Wright
A11: STORE9 | B11: 42363.084 | C11: 37845.537 | D11: 29893.777 | E11: 110102.4 | F11: =VLOOKUP(A11,Store_Dim!$A$1:$E$21,2,0) -> Moore, Padilla and Butler
A12: STORE10 | B12: 44329.974 | C12: 31658.845 | D12: 33802.896 | E12: 109791.72 | F12: =VLOOKUP(A12,Store_Dim!$A$1:$E$21,2,0) -> Hill, Wagner and Ballard
A13: STORE7 | B13: 34217.123 | C13: 26907.143 | D13: 46915.083 | E13: 108039.35 | F13: =VLOOKUP(A13,Store_Dim!$A$1:$E$21,2,0) -> Martinez-Mullins
A14: STORE14 | B14: 36010.408 | C14: 34124.633 | D14: 36113.243 | E14: 106248.28 | F14: =VLOOKUP(A14,Store_Dim!$A$1:$E$21,2,0) -> Mcdonald Inc
... A22: STORE5 | B22: 31307.002 | C22: 25208.608 | D22: 24827.98 | E22: 81343.589 | F22: =VLOOKUP(A22,Store_Dim!$A$1:$E$21,2,0) -> Gray Ltd
A23: Total sales | B23: 702459.42 | C23: 715180.71 | D23: 756754.57 | E23: 2174394.7

Sheet Stocks
A3: Row Labels | B3: Sum of Stock
A4: Beauty | B4: 4816
A5: Clothing | B5: 4931
A6: Electronics | B6: 5494
A7: Home | B7: 4521
A8: Sports | B8: 6767
A9: Grand Total | B9: 26529

Sheet Store - sales - Pivot tables
A1: Row Labels | B1: Sum of Total_Amount
A2: STORE0 | B2: 85138.555
A3: STORE1 | B3: 101060.61
A4: STORE10 | B4: 109791.72
A5: STORE11 | B5: 93048.14
A6: STORE12 | B6: 116829.22
A7: STORE13 | B7: 114401.47
A8: STORE14 | B8: 106248.28
A9: STORE15 | B9: 99679.086
A10: STORE16 | B10: 111704.94
A11: STORE17 | B11: 122176.55
A12: STORE18 | B12: 104313.05
A13: STORE19 | B13: 94225.723
... A22: Grand Total | B22: 2174394.7
A23: Row Labels | B23: Count of Store_ID
A24: COD | B24: 660
A25: Credit Card | B25: 645
A26: PayPal | B26: 695
A27: Grand Total | B27: 2000
A29: Row Labels | B29: Sum of Quantity
A30: STORE0 | B30: 204
A31: STORE1 | B31: 232
A32: STORE10 | B32: 255
A33: STORE11 | B33: 206
A34: STORE12 | B34: 259
A35: STORE13 | B35: 243
A36: STORE14 | B36: 224
A37: STORE15 | B37: 243
A38: STORE16 | B38: 249
A39: STORE17 | B39: 277
A40: STORE18 | B40: 247
A41: STORE19 | B41: 240
... A50: Grand Total | B50: 4964

Sheet Store Sales Dashboard
A1: STORE Sales Dashboard | W1: Product Sales Dashboard

Sheet Product - sales - table
A1: Sales_ID | B1: Order_Date | C1: Customer_ID | D1: Product_ID | E1: Product name | F1: Store_ID | G1: Quantity | H1: Unit_Price | I1: Discount | J1: Payment_Type | K1: Total_Amount | L1: Age | M1: Age group | N1: Gender | O1: State | P1: Stock
A2: SALE992 | B2: 45575 | C2: CUST1000 | D2: PROD40 | E2: =VLOOKUP(D2,Product_Dim!$A$1:$G$101,2,0) -> Noise-Canceling Headphones | F2: STORE7 | G2: 3 | H2: 490.02 | I2: 0.26 | J2: Credit Card | K2: 1087.8444 | L2: =VLOOKUP(C2,Customer_Dim!$A$2:$H$501,3,0) -> 55 | M2: =IF(L2<20,"Below 20", IF(L2<40,"20–39", IF(L2<60,"40–59","60+"))) -> 40–59 | N2: =VLOOKUP(C2,Customer_Dim!$A$2:$H$501,4,0) -> Male | O2: =VLOOKUP(C2,Customer_Dim!$A$2:$H$501,6,0) -> North Carolina | P2: =VLOOKUP(D2,Product_Dim!$A$1:$G$101,7,0) -> 378
A3: SALE902 | B3: 45812 | C3: CUST1000 | D3: PROD56 | E3: =VLOOKUP(D3,Product_Dim!$A$1:$G$101,2,0) -> Premium Blanket Throw | F3: STORE19 | G3: 2 | H3: 404.08 | I3: 0.07 | J3: Credit Card | K3: 751.5888 | L3: =VLOOKUP(C3,Customer_Dim!$A$2:$H$501,3,0) -> 55 | M3: =IF(L3<20,"Below 20", IF(L3<40,"20–39", IF(L3<60,"40–59","60+"))) -> 40–59 | N3: =VLOOKUP(C3,Customer_Dim!$A$2:$H$501,4,0) -> Male | O3: =VLOOKUP(C3,Customer_Dim!$A$2:$H$501,6,0) -> North Carolina | P3: =VLOOKUP(D3,Product_Dim!$A$1:$G$101,7,0) -> 190
A4: SALE388 | B4: 45780 | C4: CUST1000 | D4: PROD63 | E4: =VLOOKUP(D4,Product_Dim!$A$1:$G$101,2,0) -> Organic Sunscreen Lotion | F4: STORE16 | G4: 1 | H4: 664.71 | I4: 0.1 | J4: PayPal | K4: 598.239 | L4: =VLOOKUP(C4,Customer_Dim!$A$2:$H$501,3,0) -> 55 | M4: =IF(L4<20,"Below 20", IF(L4<40,"20–39", IF(L4<60,"40–59","60+"))) -> 40–59 | N4: =VLOOKUP(C4,Customer_Dim!$A$2:$H$501,4,0) -> Male | O4: =VLOOKUP(C4,Customer_Dim!$A$2:$H$501,6,0) -> North Carolina | P4: =VLOOKUP(D4,Product_Dim!$A$1:$G$101,7,0) -> 458
A5: SALE693 | B5: 45520 | C5: CUST1001 | D5: PROD48 | E5: =VLOOKUP(D5,Product_Dim!$A$1:$G$101,2,0) -> Car Dashboard Phone Holder | F5: STORE2 | G5: 1 | H5: 301.24 | I5: 0.11 | J5: PayPal | K5: 268.1036 | L5: =VLOOKUP(C5,Customer_Dim!$A$2:$H$501,3,0) -> 26 | M5: =IF(L5<20,"Below 20", IF(L5<40,"20–39", IF(L5<60,"40–59","60+"))) -> 20–39 | N5: =VLOOKUP(C5,Customer_Dim!$A$2:$H$501,4,0) -> Female | O5: =VLOOKUP(C5,Customer_Dim!$A$2:$H$501,6,0) -> North Dakota | P5: =VLOOKUP(D5,Product_Dim!$A$1:$G$101,7,0) -> 103
A6: SALE430 | B6: 45445 | C6: CUST1001 | D6: PROD51 | E6: =VLOOKUP(D6,Product_Dim!$A$1:$G$101,2,0) -> HDMI Cable – 2m | F6: STORE14 | G6: 3 | H6: 287.71 | I6: 0.03 | J6: COD | K6: 837.2361 | L6: =VLOOKUP(C6,Customer_Dim!$A$2:$H$501,3,0) -> 26 | M6: =IF(L6<20,"Below 20", IF(L6<40,"20–39", IF(L6<60,"40–59","60+"))) -> 20–39 | N6: =VLOOKUP(C6,Customer_Dim!$A$2:$H$501,4,0) -> Female | O6: =VLOOKUP(C6,Customer_Dim!$A$2:$H$501,6,0) -> North Dakota | P6: =VLOOKUP(D6,Product_Dim!$A$1:$G$101,7,0) -> 246
A7: SALE762 | B7: 45360 | C7: CUST1001 | D7: PROD67 | E7: =VLOOKUP(D7,Product_Dim!$A$1:$G$101,2,0) -> Smart LED Light Strip | F7: STORE0 | G7: 1 | H7: 928.72 | I7: 0.1 | J7: COD | K7: 835.848 | L7: =VLOOKUP(C7,Customer_Dim!$A$2:$H$501,3,0) -> 26 | M7: =IF(L7<20,"Below 20", IF(L7<40,"20–39", IF(L7<60,"40–59","60+"))) -> 20–39 | N7: =VLOOKUP(C7,Customer_Dim!$A$2:$H$501,4,0) -> Female | O7: =VLOOKUP(C7,Customer_Dim!$A$2:$H$501,6,0) -> North Dakota | P7: =VLOOKUP(D7,Product_Dim!$A$1:$G$101,7,0) -> 476
A8: SALE689 | B8: 45876 | C8: CUST1002 | D8: PROD54 | E8: =VLOOKUP(D8,Product_Dim!$A$1:$G$101,2,0) -> Sports Stopwatch Pro | F8: STORE5 | G8: 1 | H8: 692.75 | I8: 0.11 | J8: COD | K8: 616.5475 | L8: =VLOOKUP(C8,Customer_Dim!$A$2:$H$501,3,0) -> 29 | M8: =IF(L8<20,"Below 20", IF(L8<40,"20–39", IF(L8<60,"40–59","60+"))) -> 20–39 | N8: =VLOOKUP(C8,Customer_Dim!$A$2:$H$501,4,0) -> Female | O8: =VLOOKUP(C8,Customer_Dim!$A$2:$H$501,6,0) -> Alabama | P8: =VLOOKUP(D8,Product_Dim!$A$1:$G$101,7,0) -> 185
A9: SALE1040 | B9: 45861 | C9: CUST1002 | D9: PROD75 | E9: =VLOOKUP(D9,Product_Dim!$A$1:$G$101,2,0) -> Women's Ankle Boots | F9: STORE17 | G9: 3 | H9: 202.07 | I9: 0.23 | J9: PayPal | K9: 466.7817 | L9: =VLOOKUP(C9,Customer_Dim!$A$2:$H$501,3,0) -> 29 | M9: =IF(L9<20,"Below 20", IF(L9<40,"20–39", IF(L9<60,"40–59","60+"))) -> 20–39 | N9: =VLOOKUP(C9,Customer_Dim!$A$2:$H$501,4,0) -> Female | O9: =VLOOKUP(C9,Customer_Dim!$A$2:$H$501,6,0) -> Alabama | P9: =VLOOKUP(D9,Product_Dim!$A$1:$G$101,7,0) -> 82
A10: SALE105 | B10: 45214 | C10: CUST1002 | D10: PROD79 | E10: =VLOOKUP(D10,Product_Dim!$A$1:$G$101,2,0) -> Decorative Lamp Shade | F10: STORE17 | G10: 2 | H10: 418.23 | I10: 0.28 | J10: Credit Card | K10: 602.2512 | L10: =VLOOKUP(C10,Customer_Dim!$A$2:$H$501,3,0) -> 29 | M10: =IF(L10<20,"Below 20", IF(L10<40,"20–39", IF(L10<60,"40–59","60+"))) -> 20–39 | N10: =VLOOKUP(C10,Customer_Dim!$A$2:$H$501,4,0) -> Female | O10: =VLOOKUP(C10,Customer_Dim!$A$2:$H$501,6,0) -> Alabama | P10: =VLOOKUP(D10,Product_Dim!$A$1:$G$101,7,0) -> 469
A11: SALE741 | B11: 45372 | C11: CUST1002 | D11: PROD86 | E11: =VLOOKUP(D11,Product_Dim!$A$1:$G$101,2,0) -> Kitchen Cutting Board | F11: STORE9 | G11: 1 | H11: 431.69 | I11: 0.09 | J11: Credit Card | K11: 392.8379 | L11: =VLOOKUP(C11,Customer_Dim!$A$2:$H$501,3,0) -> 29 | M11: =IF(L11<20,"Below 20", IF(L11<40,"20–39", IF(L11<60,"40–59","60+"))) -> 20–39 | N11: =VLOOKUP(C11,Customer_Dim!$A$2:$H$501,4,0) -> Female | O11: =VLOOKUP(C11,Customer_Dim!$A$2:$H$501,6,0) -> Alabama | P11: =VLOOKUP(D11,Product_Dim!$A$1:$G$101,7,0) -> 82
A12: SALE1277 | B12: 45524 | C12: CUST1003 | D12: PROD0 | E12: =VLOOKUP(D12,Product_Dim!$A$1:$G$101,2,0) -> Brother Laser Printer | F12: STORE14 | G12: 1 | H12: 449.6 | I12: 0.01 | J12: PayPal | K12: 445.104 | L12: =VLOOKUP(C12,Customer_Dim!$A$2:$H$501,3,0) -> 59 | M12: =IF(L12<20,"Below 20", IF(L12<40,"20–39", IF(L12<60,"40–59","60+"))) -> 40–59 | N12: =VLOOKUP(C12,Customer_Dim!$A$2:$H$501,4,0) -> Female | O12: =VLOOKUP(C12,Customer_Dim!$A$2:$H$501,6,0) -> Ohio | P12: =VLOOKUP(D12,Product_Dim!$A$1:$G$101,7,0) -> 416
A13: SALE1733 | B13: 45862 | C13: CUST1003 | D13: PROD12 | E13: =VLOOKUP(D13,Product_Dim!$A$1:$G$101,2,0) -> Hair Strengthening Shampoo | F13: STORE9 | G13: 1 | H13: 437.65 | I13: 0.02 | J13: PayPal | K13: 428.897 | L13: =VLOOKUP(C13,Customer_Dim!$A$2:$H$501,3,0) -> 59 | M13: =IF(L13<20,"Below 20", IF(L13<40,"20–39", IF(L13<60,"40–59","60+"))) -> 40–59 | N13: =VLOOKUP(C13,Customer_Dim!$A$2:$H$501,4,0) -> Female | O13: =VLOOKUP(C13,Customer_Dim!$A$2:$H$501,6,0) -> Ohio | P13: =VLOOKUP(D13,Product_Dim!$A$1:$G$101,7,0) -> 460
... A655: SALE1867 | B655: 45602 | C655: CUST1148 | D655: PROD64 | E655: =VLOOKUP(D655,Product_Dim!$A$1:$G$101,2,0) -> Matte Lipstick Set | F655: STORE2 | G655: 4 | H655: 838.99 | I655: 0.16 | J655: Credit Card | K655: 2819.0064 | L655: =VLOOKUP(C655,Customer_Dim!$A$2:$H$501,3,0) -> 42 | M655: =IF(L655<20,"Below 20", IF(L655<40,"20–39", IF(L655<60,"40–59","60+"))) -> 40–59 | N655: =VLOOKUP(C655,Customer_Dim!$A$2:$H$501,4,0) -> Female | O655: =VLOOKUP(C655,Customer_Dim!$A$2:$H$501,6,0) -> Wisconsin | P655: =VLOOKUP(D655,Product_Dim!$A$1:$G$101,7,0) -> 118
A656: SALE52 | B656: 45894 | C656: CUST1148 | D656: PROD89 | E656: =VLOOKUP(D656,Product_Dim!$A$1:$G$101,2,0) -> Face Foundation Kit | F656: STORE6 | G656: 3 | J656: Credit Card | K656: 486.0633 | L656: =VLOOKUP(C656,Customer_Dim!$A$2:$H$501,3,0) -> 42 | M656: =IF(L656<20,"Below 20", IF(L656<40,"20–39", IF(L656<60,"40–59","60+"))) -> 40–59 | N656: =VLOOKUP(C656,Customer_Dim!$A$2:$H$501,4,0) -> Female | O656: =VLOOKUP(C656,Customer_Dim!$A$2:$H$501,6,0) -> Wisconsin | P656: =VLOOKUP(D656,Product_Dim!$A$1:$G$101,7,0) -> 457
A657: SALE1843 | B657: 45379 | C657: CUST1149 | D657: PROD0 | E657: =VLOOKUP(D657,Product_Dim!$A$1:$G$101,2,0) -> Brother Laser Printer | F657: STORE3 | G657: 1 | H657: 140.24 | I657: 0.27 | J657: Credit Card | K657: 102.3752 | L657: =VLOOKUP(C657,Customer_Dim!$A$2:$H$501,3,0) -> 33 | M657: =IF(L657<20,"Below 20", IF(L657<40,"20–39", IF(L657<60,"40–59","60+"))) -> 20–39 | N657: =VLOOKUP(C657,Customer_Dim!$A$2:$H$501,4,0) -> Male | O657: =VLOOKUP(C657,Customer_Dim!$A$2:$H$501,6,0) -> Florida | P657: =VLOOKUP(D657,Product_Dim!$A$1:$G$101,7,0) -> 416
A658: SALE651 | B658: 45721 | C658: CUST1149 | D658: PROD71 | E658: =VLOOKUP(D658,Product_Dim!$A$1:$G$101,2,0) -> Hair Repair Oil Treatment | F658: STORE1 | G658: 1 | H658: 888.05 | I658: 0.2 | J658: PayPal | K658: 710.44 | L658: =VLOOKUP(C658,Customer_Dim!$A$2:$H$501,3,0) -> 33 | M658: =IF(L658<20,"Below 20", IF(L658<40,"20–39", IF(L658<60,"40–59","60+"))) -> 20–39 | N658: =VLOOKUP(C658,Customer_Dim!$A$2:$H$501,4,0) -> Male | O658: =VLOOKUP(C658,Customer_Dim!$A$2:$H$501,6,0) -> Florida | P658: =VLOOKUP(D658,Product_Dim!$A$1:$G$101,7,0) -> 383
A659: SALE643 | B659: 45586 | C659: CUST1149 | D659: PROD76 | E659: =VLOOKUP(D659,Product_Dim!$A$1:$G$101,2,0) -> Wireless Mouse | F659: STORE6 | G659: 3 | H659: 89.78 | I659: 0.2 | J659: COD | K659: 215.472 | L659: =VLOOKUP(C659,Customer_Dim!$A$2:$H$501,3,0) -> 33 | M659: =IF(L659<20,"Below 20", IF(L659<40,"20–39", IF(L659<60,"40–59","60+"))) -> 20–39 | N659: =VLOOKUP(C659,Customer_Dim!$A$2:$H$501,4,0) -> Male | O659: =VLOOKUP(C659,Customer_Dim!$A$2:$H$501,6,0) -> Florida | P659: =VLOOKUP(D659,Product_Dim!$A$1:$G$101,7,0) -> 320
A660: SALE565 | B660: 45843 | C660: CUST1149 | D660: PROD90 | E660: =VLOOKUP(D660,Product_Dim!$A$1:$G$101,2,0) -> Gaming Mouse Pad XL | F660: STORE12 | G660: 1 | H660: 780.16 | I660: 0.02 | J660: COD | K660: 764.5568 | L660: =VLOOKUP(C660,Customer_Dim!$A$2:$H$501,3,0) -> 33 | M660: =IF(L660<20,"Below 20", IF(L660<40,"20–39", IF(L660<60,"40–59","60+"))) -> 20–39 | N660: =VLOOKUP(C660,Customer_Dim!$A$2:$H$501,4,0) -> Male | O660: =VLOOKUP(C660,Customer_Dim!$A$2:$H$501,6,0) -> Florida | P660: =VLOOKUP(D660,Product_Dim!$A$1:$G$101,7,0) -> 361
A661: SALE341 | B661: 45727 | C661: CUST1150 | D661: PROD11 | E661: =VLOOKUP(D661,Product_Dim!$A$1:$G$101,2,0) -> HD Smart TV Stick | F661: STORE15 | G661: 3 | H661: 121.64 | I661: 0.07 | J661: PayPal | K661: 339.3756 | L661: =VLOOKUP(C661,Customer_Dim!$A$2:$H$501,3,0) -> 24 | M661: =IF(L661<20,"Below 20", IF(L661<40,"20–39", IF(L661<60,"40–59","60+"))) -> 20–39 | N661: =VLOOKUP(C661,Customer_Dim!$A$2:$H$501,4,0) -> Male | O661: =VLOOKUP(C661,Customer_Dim!$A$2:$H$501,6,0) -> Mississippi | P661: =VLOOKUP(D661,Product_Dim!$A$1:$G$101,7,0) -> 0
A662: SALE705 | B662: 45803 | C662: CUST1151 | D662: PROD24 | E662: =VLOOKUP(D662,Product_Dim!$A$1:$G$101,2,0) -> Foldable Camping Chair | F662: STORE18 | G662: 4 | H662: 757.9 | I662: 0.22 | J662: PayPal | K662: 2364.648 | L662: =VLOOKUP(C662,Customer_Dim!$A$2:$H$501,3,0) -> 25 | M662: =IF(L662<20,"Below 20", IF(L662<40,"20–39", IF(L662<60,"40–59","60+"))) -> 20–39 | N662: =VLOOKUP(C662,Customer_Dim!$A$2:$H$501,4,0) -> Female | O662: =VLOOKUP(C662,Customer_Dim!$A$2:$H$501,6,0) -> Oregon | P662: =VLOOKUP(D662,Product_Dim!$A$1:$G$101,7,0) -> 340
A663: SALE1070 | B663: 45576 | C663: CUST1151 | D663: PROD50 | E663: =VLOOKUP(D663,Product_Dim!$A$1:$G$101,2,0) -> Boxing Hand Wraps | F663: STORE2 | G663: 4 | H663: 694.61 | I663: 0.18 | J663: COD | K663: 2278.3208 | L663: =VLOOKUP(C663,Customer_Dim!$A$2:$H$501,3,0) -> 25 | M663: =IF(L663<20,"Below 20", IF(L663<40,"20–39", IF(L663<60,"40–59","60+"))) -> 20–39 | N663: =VLOOKUP(C663,Customer_Dim!$A$2:$H$501,4,0) -> Female | O663: =VLOOKUP(C663,Customer_Dim!$A$2:$H$501,6,0) -> Oregon | P663: =VLOOKUP(D663,Product_Dim!$A$1:$G$101,7,0) -> 260
A664: SALE1112 | B664: 45316 | C664: CUST1151 | D664: PROD73 | E664: =VLOOKUP(D664,Product_Dim!$A$1:$G$101,2,0) -> Shin Guards – Adult | F664: STORE5 | G664: 2 | H664: 644 | I664: 0.04 | J664: PayPal | K664: 1236.48 | L664: =VLOOKUP(C664,Customer_Dim!$A$2:$H$501,3,0) -> 25 | M664: =IF(L664<20,"Below 20", IF(L664<40,"20–39", IF(L664<60,"40–59","60+"))) -> 20–39 | N664: =VLOOKUP(C664,Customer_Dim!$A$2:$H$501,4,0) -> Female | O664: =VLOOKUP(C664,Customer_Dim!$A$2:$H$501,6,0) -> Oregon | P664: =VLOOKUP(D664,Product_Dim!$A$1:$G$101,7,0) -> 359
A665: SALE1664 | B665: 45798 | C665: CUST1152 | D665: PROD39 | E665: =VLOOKUP(D665,Product_Dim!$A$1:$G$101,2,0) -> Portable Power Bank | F665: STORE14 | G665: 3 | H665: 343.97 | I665: 0.04 | J665: COD | K665: 990.6336 | L665: =VLOOKUP(C665,Customer_Dim!$A$2:$H$501,3,0) -> 41 | M665: =IF(L665<20,"Below 20", IF(L665<40,"20–39", IF(L665<60,"40–59","60+"))) -> 40–59 | N665: =VLOOKUP(C665,Customer_Dim!$A$2:$H$501,4,0) -> Female | O665: =VLOOKUP(C665,Customer_Dim!$A$2:$H$501,6,0) -> Missouri | P665: =VLOOKUP(D665,Product_Dim!$A$1:$G$101,7,0) -> 301
A666: SALE1420 | B666: 45875 | C666: CUST1152 | D666: PROD53 | E666: =VLOOKUP(D666,Product_Dim!$A$1:$G$101,2,0) -> Men's Track Pants | F666: STORE19 | G666: 2 | H666: 664.5 | I666: 0.23 | J666: Credit Card | K666: 1023.33 | L666: =VLOOKUP(C666,Customer_Dim!$A$2:$H$501,3,0) -> 41 | M666: =IF(L666<20,"Below 20", IF(L666<40,"20–39", IF(L666<60,"40–59","60+"))) -> 40–59 | N666: =VLOOKUP(C666,Customer_Dim!$A$2:$H$501,4,0) -> Female | O666: =VLOOKUP(C666,Customer_Dim!$A$2:$H$501,6,0) -> Missouri | P666: =VLOOKUP(D666,Product_Dim!$A$1:$G$101,7,0) -> 125
A667: SALE7 | B667: 45248 | C667: CUST1152 | D667: PROD70 | E667: =VLOOKUP(D667,Product_Dim!$A$1:$G$101,2,0) -> Kitchen Storage Rack | F667: STORE8 | G667: 4 | H667: 342.39 | I667: 0.23 | J667: PayPal | K667: 1054.5612 | L667: =VLOOKUP(C667,Customer_Dim!$A$2:$H$501,3,0) -> 41 | M667: =IF(L667<20,"Below 20", IF(L667<40,"20–39", IF(L667<60,"40–59","60+"))) -> 40–59 | N667: =VLOOKUP(C667,Customer_Dim!$A$2:$H$501,4,0) -> Female | O667: =VLOOKUP(C667,Customer_Dim!$A$2:$H$501,6,0) -> Missouri | P667: =VLOOKUP(D667,Product_Dim!$A$1:$G$101,7,0) -> 89
A668: SALE114 | B668: 45482 | C668: CUST1152 | D668: PROD91 | E668: =VLOOKUP(D668,Product_Dim!$A$1:$G$101,2,0) -> Women's High Heels | F668: STORE4 | G668: 2 | H668: 731.01 | I668: 0.05 | J668: PayPal | K668: 1388.919 | L668: =VLOOKUP(C668,Customer_Dim!$A$2:$H$501,3,0) -> 41 | M668: =IF(L668<20,"Below 20", IF(L668<40,"20–39", IF(L668<60,"40–59","60+"))) -> 40–59 | N668: =VLOOKUP(C668,Customer_Dim!$A$2:$H$501,4,0) -> Female | O668: =VLOOKUP(C668,Customer_Dim!$A$2:$H$501,6,0) -> Missouri | P668: =VLOOKUP(D668,Product_Dim!$A$1:$G$101,7,0) -> 496
... A922: SALE839 | B922: 45755 | C922: CUST1213 | D922: PROD87 | E922: =VLOOKUP(D922,Product_Dim!$A$1:$G$101,2,0) -> LED Bedside Lamp | F922: STORE0 | G922: 3 | H922: 693.42 | I922: 0.08 | J922: PayPal | K922: 1913.8392 | L922: =VLOOKUP(C922,Customer_Dim!$A$2:$H$501,3,0) -> 42 | M922: =IF(L922<20,"Below 20", IF(L922<40,"20–39", IF(L922<60,"40–59","60+"))) -> 40–59 | N922: =VLOOKUP(C922,Customer_Dim!$A$2:$H$501,4,0) -> Female | O922: =VLOOKUP(C922,Customer_Dim!$A$2:$H$501,6,0) -> North Dakota | P922: =VLOOKUP(D922,Product_Dim!$A$1:$G$101,7,0) -> 220
A923: SALE26 | B923: 45294 | C923: CUST1213 | D923: PROD98 | E923: =VLOOKUP(D923,Product_Dim!$A$1:$G$101,2,0) -> Portable Bluetooth Speaker | F923: STORE8 | G923: 4 | H923: 156.16 | J923: Credit Card | K923: 599.6544 | L923: =VLOOKUP(C923,Customer_Dim!$A$2:$H$501,3,0) -> 42 | M923: =IF(L923<20,"Below 20", IF(L923<40,"20–39", IF(L923<60,"40–59","60+"))) -> 40–59 | N923: =VLOOKUP(C923,Customer_Dim!$A$2:$H$501,4,0) -> Female | O923: =VLOOKUP(C923,Customer_Dim!$A$2:$H$501,6,0) -> North Dakota | P923: =VLOOKUP(D923,Product_Dim!$A$1:$G$101,7,0) -> 73
A924: SALE351 | B924: 45621 | C924: CUST1214 | D924: PROD12 | E924: =VLOOKUP(D924,Product_Dim!$A$1:$G$101,2,0) -> Hair Strengthening Shampoo | F924: STORE18 | G924: 3 | H924: 877.71 | I924: 0.12 | J924: PayPal | K924: 2317.1544 | L924: =VLOOKUP(C924,Customer_Dim!$A$2:$H$501,3,0) -> 61 | M924: =IF(L924<20,"Below 20", IF(L924<40,"20–39", IF(L924<60,"40–59","60+"))) -> 60+ | N924: =VLOOKUP(C924,Customer_Dim!$A$2:$H$501,4,0) -> Male | O924: =VLOOKUP(C924,Customer_Dim!$A$2:$H$501,6,0) -> Montana | P924: =VLOOKUP(D924,Product_Dim!$A$1:$G$101,7,0) -> 460
A925: SALE588 | B925: 45357 | C925: CUST1214 | D925: PROD71 | E925: =VLOOKUP(D925,Product_Dim!$A$1:$G$101,2,0) -> Hair Repair Oil Treatment | F925: STORE18 | G925: 1 | H925: 250.95 | I925: 0.03 | J925: PayPal | K925: 243.4215 | L925: =VLOOKUP(C925,Customer_Dim!$A$2:$H$501,3,0) -> 61 | M925: =IF(L925<20,"Below 20", IF(L925<40,"20–39", IF(L925<60,"40–59","60+"))) -> 60+ | N925: =VLOOKUP(C925,Customer_Dim!$A$2:$H$501,4,0) -> Male | O925: =VLOOKUP(C925,Customer_Dim!$A$2:$H$501,6,0) -> Montana | P925: =VLOOKUP(D925,Product_Dim!$A$1:$G$101,7,0) -> 383
A926: SALE1792 | B926: 45387 | C926: CUST1214 | D926: PROD73 | E926: =VLOOKUP(D926,Product_Dim!$A$1:$G$101,2,0) -> Shin Guards – Adult | F926: STORE14 | G926: 2 | H926: 720.15 | I926: 0.22 | J926: COD | K926: 1123.434 | L926: =VLOOKUP(C926,Customer_Dim!$A$2:$H$501,3,0) -> 61 | M926: =IF(L926<20,"Below 20", IF(L926<40,"20–39", IF(L926<60,"40–59","60+"))) -> 60+ | N926: =VLOOKUP(C926,Customer_Dim!$A$2:$H$501,4,0) -> Male | O926: =VLOOKUP(C926,Customer_Dim!$A$2:$H$501,6,0) -> Montana | P926: =VLOOKUP(D926,Product_Dim!$A$1:$G$101,7,0) -> 359
A927: SALE109 | B927: 45738 | C927: CUST1214 | D927: PROD91 | E927: =VLOOKUP(D927,Product_Dim!$A$1:$G$101,2,0) -> Women's High Heels | F927: STORE0 | G927: 3 | H927: 376.46 | I927: 0.09 | J927: COD | K927: 1027.7358 | L927: =VLOOKUP(C927,Customer_Dim!$A$2:$H$501,3,0) -> 61 | M927: =IF(L927<20,"Below 20", IF(L927<40,"20–39", IF(L927<60,"40–59","60+"))) -> 60+ | N927: =VLOOKUP(C927,Customer_Dim!$A$2:$H$501,4,0) -> Male | O927: =VLOOKUP(C927,Customer_Dim!$A$2:$H$501,6,0) -> Montana | P927: =VLOOKUP(D927,Product_Dim!$A$1:$G$101,7,0) -> 496
A928: SALE456 | B928: 45527 | C928: CUST1215 | D928: PROD32 | E928: =VLOOKUP(D928,Product_Dim!$A$1:$G$101,2,0) -> Vitamin C Face Serum | F928: STORE9 | G928: 4 | H928: 315.95 | I928: 0.19 | J928: COD | K928: 1023.678 | L928: =VLOOKUP(C928,Customer_Dim!$A$2:$H$501,3,0) -> 50 | M928: =IF(L928<20,"Below 20", IF(L928<40,"20–39", IF(L928<60,"40–59","60+"))) -> 40–59 | N928: =VLOOKUP(C928,Customer_Dim!$A$2:$H$501,4,0) -> Female | O928: =VLOOKUP(C928,Customer_Dim!$A$2:$H$501,6,0) -> Oregon | P928: =VLOOKUP(D928,Product_Dim!$A$1:$G$101,7,0) -> 244
A929: SALE926 | B929: 45369 | C929: CUST1215 | D929: PROD67 | E929: =VLOOKUP(D929,Product_Dim!$A$1:$G$101,2,0) -> Smart LED Light Strip | F929: STORE19 | G929: 3 | H929: 968.88 | I929: 0.15 | J929: Credit Card | K929: 2470.644 | L929: =VLOOKUP(C929,Customer_Dim!$A$2:$H$501,3,0) -> 50 | M929: =IF(L929<20,"Below 20", IF(L929<40,"20–39", IF(L929<60,"40–59","60+"))) -> 40–59 | N929: =VLOOKUP(C929,Customer_Dim!$A$2:$H$501,4,0) -> Female | O929: =VLOOKUP(C929,Customer_Dim!$A$2:$H$501,6,0) -> Oregon | P929: =VLOOKUP(D929,Product_Dim!$A$1:$G$101,7,0) -> 476
A930: SALE299 | B930: 45348 | C930: CUST1216 | D930: PROD22 | E930: =VLOOKUP(D930,Product_Dim!$A$1:$G$101,2,0) -> Carbon Fiber Tennis Racket | F930: STORE19 | G930: 2 | H930: 873.1 | I930: 0.12 | J930: PayPal | K930: 1536.656 | L930: =VLOOKUP(C930,Customer_Dim!$A$2:$H$501,3,0) -> 44 | M930: =IF(L930<20,"Below 20", IF(L930<40,"20–39", IF(L930<60,"40–59","60+"))) -> 40–59 | N930: =VLOOKUP(C930,Customer_Dim!$A$2:$H$501,4,0) -> Male | O930: =VLOOKUP(C930,Customer_Dim!$A$2:$H$501,6,0) -> California | P930: =VLOOKUP(D930,Product_Dim!$A$1:$G$101,7,0) -> 432
A931: SALE364 | B931: 45723 | C931: CUST1216 | D931: PROD35 | E931: =VLOOKUP(D931,Product_Dim!$A$1:$G$101,2,0) -> Bedroom Table Lamp | F931: STORE18 | G931: 1 | H931: 213.69 | I931: 0.28 | J931: COD | K931: 153.8568 | L931: =VLOOKUP(C931,Customer_Dim!$A$2:$H$501,3,0) -> 44 | M931: =IF(L931<20,"Below 20", IF(L931<40,"20–39", IF(L931<60,"40–59","60+"))) -> 40–59 | N931: =VLOOKUP(C931,Customer_Dim!$A$2:$H$501,4,0) -> Male | O931: =VLOOKUP(C931,Customer_Dim!$A$2:$H$501,6,0) -> California | P931: =VLOOKUP(D931,Product_Dim!$A$1:$G$101,7,0) -> 329
A932: SALE605 | B932: 45222 | C932: CUST1216 | D932: PROD72 | E932: =VLOOKUP(D932,Product_Dim!$A$1:$G$101,2,0) -> Professional Jump Rope | F932: STORE0 | G932: 1 | H932: 61.11 | I932: 0.1 | J932: PayPal | K932: 54.999 | L932: =VLOOKUP(C932,Customer_Dim!$A$2:$H$501,3,0) -> 44 | M932: =IF(L932<20,"Below 20", IF(L932<40,"20–39", IF(L932<60,"40–59","60+"))) -> 40–59 | N932: =VLOOKUP(C932,Customer_Dim!$A$2:$H$501,4,0) -> Male | O932: =VLOOKUP(C932,Customer_Dim!$A$2:$H$501,6,0) -> California | P932: =VLOOKUP(D932,Product_Dim!$A$1:$G$101,7,0) -> 300
A933: SALE239 | B933: 45861 | C933: CUST1216 | D933: PROD86 | E933: =VLOOKUP(D933,Product_Dim!$A$1:$G$101,2,0) -> Kitchen Cutting Board | F933: STORE8 | G933: 3 | H933: 91.7 | I933: 0.08 | J933: COD | K933: 253.092 | L933: =VLOOKUP(C933,Customer_Dim!$A$2:$H$501,3,0) -> 44 | M933: =IF(L933<20,"Below 20", IF(L933<40,"20–39", IF(L933<60,"40–59","60+"))) -> 40–59 | N933: =VLOOKUP(C933,Customer_Dim!$A$2:$H$501,4,0) -> Male | O933: =VLOOKUP(C933,Customer_Dim!$A$2:$H$501,6,0) -> California | P933: =VLOOKUP(D933,Product_Dim!$A$1:$G$101,7,0) -> 82
A934: SALE1702 | B934: 45268 | C934: CUST1217 | D934: PROD37 | E934: =VLOOKUP(D934,Product_Dim!$A$1:$G$101,2,0) -> Men's Casual Sneakers | F934: STORE7 | G934: 2 | H934: 985.79 | I934: 0.04 | J934: PayPal | K934: 1892.7168 | L934: =VLOOKUP(C934,Customer_Dim!$A$2:$H$501,3,0) -> 42 | M934: =IF(L934<20,"Below 20", IF(L934<40,"20–39", IF(L934<60,"40–59","60+"))) -> 40–59 | N934: =VLOOKUP(C934,Customer_Dim!$A$2:$H$501,4,0) -> Male | O934: =VLOOKUP(C934,Customer_Dim!$A$2:$H$501,6,0) -> Missouri | P934: =VLOOKUP(D934,Product_Dim!$A$1:$G$101,7,0) -> 214
A935: SALE1547 | B935: 45434 | C935: CUST1217 | D935: PROD43 | E935: =VLOOKUP(D935,Product_Dim!$A$1:$G$101,2,0) -> USB External Hard Drive | F935: STORE19 | G935: 1 | H935: 661.77 | I935: 0.03 | J935: PayPal | K935: 641.9169 | L935: =VLOOKUP(C935,Customer_Dim!$A$2:$H$501,3,0) -> 42 | M935: =IF(L935<20,"Below 20", IF(L935<40,"20–39", IF(L935<60,"40–59","60+"))) -> 40–59 | N935: =VLOOKUP(C935,Customer_Dim!$A$2:$H$501,4,0) -> Male | O935: =VLOOKUP(C935,Customer_Dim!$A$2:$H$501,6,0) -> Missouri | P935: =VLOOKUP(D935,Product_Dim!$A$1:$G$101,7,0) -> 266
... A1015: SALE61 | B1015: 45716 | C1015: CUST1239 | D1015: PROD19 | E1015: =VLOOKUP(D1015,Product_Dim!$A$1:$G$101,2,0) -> Knee Support Brace | F1015: STORE7 | G1015: 1 | H1015: 374.92 | I1015: 0.18 | J1015: PayPal | K1015: 307.4344 | L1015: =VLOOKUP(C1015,Customer_Dim!$A$2:$H$501,3,0) -> 58 | M1015: =IF(L1015<20,"Below 20", IF(L1015<40,"20–39", IF(L1015<60,"40–59","60+"))) -> 40–59 | N1015: =VLOOKUP(C1015,Customer_Dim!$A$2:$H$501,4,0) -> Female | O1015: =VLOOKUP(C1015,Customer_Dim!$A$2:$H$501,6,0) -> Nevada | P1015: =VLOOKUP(D1015,Product_Dim!$A$1:$G$101,7,0) -> 65
A1016: SALE19 | B1016: 45369 | C1016: CUST1239 | D1016: PROD60 | E1016: =VLOOKUP(D1016,Product_Dim!$A$1:$G$101,2,0) -> Luxury Perfume Spray | F1016: STORE13 | G1016: 4 | I1016: 0.04 | J1016: COD | K1016: 1782.4512 | L1016: =VLOOKUP(C1016,Customer_Dim!$A$2:$H$501,3,0) -> 58 | M1016: =IF(L1016<20,"Below 20", IF(L1016<40,"20–39", IF(L1016<60,"40–59","60+"))) -> 40–59 | N1016: =VLOOKUP(C1016,Customer_Dim!$A$2:$H$501,4,0) -> Female | O1016: =VLOOKUP(C1016,Customer_Dim!$A$2:$H$501,6,0) -> Nevada | P1016: =VLOOKUP(D1016,Product_Dim!$A$1:$G$101,7,0) -> 444
A1017: SALE379 | B1017: 45240 | C1017: CUST1239 | D1017: PROD78 | E1017: =VLOOKUP(D1017,Product_Dim!$A$1:$G$101,2,0) -> Essential Oil Diffuser | F1017: STORE1 | G1017: 3 | H1017: 636.03 | I1017: 0.06 | J1017: COD | K1017: 1793.6046 | L1017: =VLOOKUP(C1017,Customer_Dim!$A$2:$H$501,3,0) -> 58 | M1017: =IF(L1017<20,"Below 20", IF(L1017<40,"20–39", IF(L1017<60,"40–59","60+"))) -> 40–59 | N1017: =VLOOKUP(C1017,Customer_Dim!$A$2:$H$501,4,0) -> Female | O1017: =VLOOKUP(C1017,Customer_Dim!$A$2:$H$501,6,0) -> Nevada | P1017: =VLOOKUP(D1017,Product_Dim!$A$1:$G$101,7,0) -> 400
A1018: SALE779 | B1018: 45386 | C1018: CUST1239 | D1018: PROD86 | E1018: =VLOOKUP(D1018,Product_Dim!$A$1:$G$101,2,0) -> Kitchen Cutting Board | F1018: STORE3 | G1018: 3 | H1018: 413.74 | I1018: 0.01 | J1018: Credit Card | K1018: 1228.8078 | L1018: =VLOOKUP(C1018,Customer_Dim!$A$2:$H$501,3,0) -> 58 | M1018: =IF(L1018<20,"Below 20", IF(L1018<40,"20–39", IF(L1018<60,"40–59","60+"))) -> 40–59 | N1018: =VLOOKUP(C1018,Customer_Dim!$A$2:$H$501,4,0) -> Female | O1018: =VLOOKUP(C1018,Customer_Dim!$A$2:$H$501,6,0) -> Nevada | P1018: =VLOOKUP(D1018,Product_Dim!$A$1:$G$101,7,0) -> 82
A1019: SALE1236 | B1019: 45908 | C1019: CUST1239 | D1019: PROD86 | E1019: =VLOOKUP(D1019,Product_Dim!$A$1:$G$101,2,0) -> Kitchen Cutting Board | F1019: STORE7 | G1019: 1 | H1019: 729.05 | I1019: 0.06 | J1019: COD | K1019: 685.307 | L1019: =VLOOKUP(C1019,Customer_Dim!$A$2:$H$501,3,0) -> 58 | M1019: =IF(L1019<20,"Below 20", IF(L1019<40,"20–39", IF(L1019<60,"40–59","60+"))) -> 40–59 | N1019: =VLOOKUP(C1019,Customer_Dim!$A$2:$H$501,4,0) -> Female | O1019: =VLOOKUP(C1019,Customer_Dim!$A$2:$H$501,6,0) -> Nevada | P1019: =VLOOKUP(D1019,Product_Dim!$A$1:$G$101,7,0) -> 82
A1020: SALE892 | B1020: 45895 | C1020: CUST1239 | D1020: PROD92 | E1020: =VLOOKUP(D1020,Product_Dim!$A$1:$G$101,2,0) -> Microwave Oven | F1020: STORE0 | G1020: 1 | H1020: 533.8 | I1020: 0.27 | J1020: COD | K1020: 389.674 | L1020: =VLOOKUP(C1020,Customer_Dim!$A$2:$H$501,3,0) -> 58 | M1020: =IF(L1020<20,"Below 20", IF(L1020<40,"20–39", IF(L1020<60,"40–59","60+"))) -> 40–59 | N1020: =VLOOKUP(C1020,Customer_Dim!$A$2:$H$501,4,0) -> Female | O1020: =VLOOKUP(C1020,Customer_Dim!$A$2:$H$501,6,0) -> Nevada | P1020: =VLOOKUP(D1020,Product_Dim!$A$1:$G$101,7,0) -> 191
A1021: SALE494 | B1021: 45501 | C1021: CUST1240 | D1021: PROD18 | E1021: =VLOOKUP(D1021,Product_Dim!$A$1:$G$101,2,0) -> Women's Denim Jeans | F1021: STORE0 | G1021: 1 | H1021: 917.17 | I1021: 0.13 | J1021: COD | K1021: 797.9379 | L1021: =VLOOKUP(C1021,Customer_Dim!$A$2:$H$501,3,0) -> 59 | M1021: =IF(L1021<20,"Below 20", IF(L1021<40,"20–39", IF(L1021<60,"40–59","60+"))) -> 40–59 | N1021: =VLOOKUP(C1021,Customer_Dim!$A$2:$H$501,4,0) -> Female | O1021: =VLOOKUP(C1021,Customer_Dim!$A$2:$H$501,6,0) -> Michigan | P1021: =VLOOKUP(D1021,Product_Dim!$A$1:$G$101,7,0) -> 343
A1022: SALE692 | B1022: 45650 | C1022: CUST1240 | D1022: PROD26 | E1022: =VLOOKUP(D1022,Product_Dim!$A$1:$G$101,2,0) -> Wireless Bluetooth Speaker | F1022: STORE19 | G1022: 2 | H1022: 800.84 | I1022: 0.27 | J1022: COD | K1022: 1169.2264 | L1022: =VLOOKUP(C1022,Customer_Dim!$A$2:$H$501,3,0) -> 59 | M1022: =IF(L1022<20,"Below 20", IF(L1022<40,"20–39", IF(L1022<60,"40–59","60+"))) -> 40–59 | N1022: =VLOOKUP(C1022,Customer_Dim!$A$2:$H$501,4,0) -> Female | O1022: =VLOOKUP(C1022,Customer_Dim!$A$2:$H$501,6,0) -> Michigan | P1022: =VLOOKUP(D1022,Product_Dim!$A$1:$G$101,7,0) -> 213
A1023: SALE1639 | B1023: 45478 | C1023: CUST1240 | D1023: PROD26 | E1023: =VLOOKUP(D1023,Product_Dim!$A$1:$G$101,2,0) -> Wireless Bluetooth Speaker | F1023: STORE17 | G1023: 3 | H1023: 543.93 | I1023: 0.3 | J1023: COD | K1023: 1142.253 | L1023: =VLOOKUP(C1023,Customer_Dim!$A$2:$H$501,3,0) -> 59 | M1023: =IF(L1023<20,"Below 20", IF(L1023<40,"20–39", IF(L1023<60,"40–59","60+"))) -> 40–59 | N1023: =VLOOKUP(C1023,Customer_Dim!$A$2:$H$501,4,0) -> Female | O1023: =VLOOKUP(C1023,Customer_Dim!$A$2:$H$501,6,0) -> Michigan | P1023: =VLOOKUP(D1023,Product_Dim!$A$1:$G$101,7,0) -> 213
A1024: SALE253 | B1024: 45876 | C1024: CUST1240 | D1024: PROD92 | E1024: =VLOOKUP(D1024,Product_Dim!$A$1:$G$101,2,0) -> Microwave Oven | F1024: STORE18 | G1024: 2 | H1024: 239.92 | I1024: 0.16 | J1024: Credit Card | K1024: 403.0656 | L1024: =VLOOKUP(C1024,Customer_Dim!$A$2:$H$501,3,0) -> 59 | M1024: =IF(L1024<20,"Below 20", IF(L1024<40,"20–39", IF(L1024<60,"40–59","60+"))) -> 40–59 | N1024: =VLOOKUP(C1024,Customer_Dim!$A$2:$H$501,4,0) -> Female | O1024: =VLOOKUP(C1024,Customer_Dim!$A$2:$H$501,6,0) -> Michigan | P1024: =VLOOKUP(D1024,Product_Dim!$A$1:$G$101,7,0) -> 191
A1025: SALE355 | B1025: 45304 | C1025: CUST1241 | D1025: PROD15 | E1025: =VLOOKUP(D1025,Product_Dim!$A$1:$G$101,2,0) -> 4K Home Projector | F1025: STORE15 | G1025: 2 | H1025: 899.27 | I1025: 0.17 | J1025: Credit Card | K1025: 1492.7882 | L1025: =VLOOKUP(C1025,Customer_Dim!$A$2:$H$501,3,0) -> 31 | M1025: =IF(L1025<20,"Below 20", IF(L1025<40,"20–39", IF(L1025<60,"40–59","60+"))) -> 20–39 | N1025: =VLOOKUP(C1025,Customer_Dim!$A$2:$H$501,4,0) -> Male | O1025: =VLOOKUP(C1025,Customer_Dim!$A$2:$H$501,6,0) -> Virginia | P1025: =VLOOKUP(D1025,Product_Dim!$A$1:$G$101,7,0) -> 301
A1026: SALE722 | B1026: 45379 | C1026: CUST1241 | D1026: PROD15 | E1026: =VLOOKUP(D1026,Product_Dim!$A$1:$G$101,2,0) -> 4K Home Projector | F1026: STORE14 | G1026: 1 | H1026: 31.36 | I1026: 0.21 | J1026: COD | K1026: 24.7744 | L1026: =VLOOKUP(C1026,Customer_Dim!$A$2:$H$501,3,0) -> 31 | M1026: =IF(L1026<20,"Below 20", IF(L1026<40,"20–39", IF(L1026<60,"40–59","60+"))) -> 20–39 | N1026: =VLOOKUP(C1026,Customer_Dim!$A$2:$H$501,4,0) -> Male | O1026: =VLOOKUP(C1026,Customer_Dim!$A$2:$H$501,6,0) -> Virginia | P1026: =VLOOKUP(D1026,Product_Dim!$A$1:$G$101,7,0) -> 301
A1027: SALE776 | B1027: 45472 | C1027: CUST1241 | D1027: PROD20 | E1027: =VLOOKUP(D1027,Product_Dim!$A$1:$G$101,2,0) -> Outdoor Sports Water Bottle | F1027: STORE4 | G1027: 3 | H1027: 909.25 | I1027: 0.29 | J1027: COD | K1027: 1936.7025 | L1027: =VLOOKUP(C1027,Customer_Dim!$A$2:$H$501,3,0) -> 31 | M1027: =IF(L1027<20,"Below 20", IF(L1027<40,"20–39", IF(L1027<60,"40–59","60+"))) -> 20–39 | N1027: =VLOOKUP(C1027,Customer_Dim!$A$2:$H$501,4,0) -> Male | O1027: =VLOOKUP(C1027,Customer_Dim!$A$2:$H$501,6,0) -> Virginia | P1027: =VLOOKUP(D1027,Product_Dim!$A$1:$G$101,7,0) -> 0
A1028: SALE1804 | B1028: 45941 | C1028: CUST1241 | D1028: PROD25 | E1028: =VLOOKUP(D1028,Product_Dim!$A$1:$G$101,2,0) -> Women's Scarf Set | F1028: STORE18 | G1028: 1 | H1028: 401.18 | I1028: 0.15 | J1028: COD | K1028: 341.003 | L1028: =VLOOKUP(C1028,Customer_Dim!$A$2:$H$501,3,0) -> 31 | M1028: =IF(L1028<20,"Below 20", IF(L1028<40,"20–39", IF(L1028<60,"40–59","60+"))) -> 20–39 | N1028: =VLOOKUP(C1028,Customer_Dim!$A$2:$H$501,4,0) -> Male | O1028: =VLOOKUP(C1028,Customer_Dim!$A$2:$H$501,6,0) -> Virginia | P1028: =VLOOKUP(D1028,Product_Dim!$A$1:$G$101,7,0) -> 268
... A1054: SALE750 | B1054: 45778 | C1054: CUST1248 | D1054: PROD34 | E1054: =VLOOKUP(D1054,Product_Dim!$A$1:$G$101,2,0) -> Gaming Mechanical Keyboard | F1054: STORE3 | G1054: 3 | H1054: 35.16 | I1054: 0.04 | J1054: COD | K1054: 101.2608 | L1054: =VLOOKUP(C1054,Customer_Dim!$A$2:$H$501,3,0) -> 19 | M1054: =IF(L1054<20,"Below 20", IF(L1054<40,"20–39", IF(L1054<60,"40–59","60+"))) -> Below 20 | N1054: =VLOOKUP(C1054,Customer_Dim!$A$2:$H$501,4,0) -> Male | O1054: =VLOOKUP(C1054,Customer_Dim!$A$2:$H$501,6,0) -> Nevada | P1054: =VLOOKUP(D1054,Product_Dim!$A$1:$G$101,7,0) -> 86
A1055: SALE259 | B1055: 45773 | C1055: CUST1248 | D1055: PROD35 | E1055: =VLOOKUP(D1055,Product_Dim!$A$1:$G$101,2,0) -> Bedroom Table Lamp | F1055: STORE2 | G1055: 2 | H1055: 355.3 | J1055: PayPal | K1055: 589.798 | L1055: =VLOOKUP(C1055,Customer_Dim!$A$2:$H$501,3,0) -> 19 | M1055: =IF(L1055<20,"Below 20", IF(L1055<40,"20–39", IF(L1055<60,"40–59","60+"))) -> Below 20 | N1055: =VLOOKUP(C1055,Customer_Dim!$A$2:$H$501,4,0) -> Male | O1055: =VLOOKUP(C1055,Customer_Dim!$A$2:$H$501,6,0) -> Nevada | P1055: =VLOOKUP(D1055,Product_Dim!$A$1:$G$101,7,0) -> 329
A1056: SALE967 | B1056: 45783 | C1056: CUST1248 | D1056: PROD39 | E1056: =VLOOKUP(D1056,Product_Dim!$A$1:$G$101,2,0) -> Portable Power Bank | F1056: STORE18 | G1056: 3 | H1056: 529.89 | I1056: 0.21 | J1056: Credit Card | K1056: 1255.8393 | L1056: =VLOOKUP(C1056,Customer_Dim!$A$2:$H$501,3,0) -> 19 | M1056: =IF(L1056<20,"Below 20", IF(L1056<40,"20–39", IF(L1056<60,"40–59","60+"))) -> Below 20 | N1056: =VLOOKUP(C1056,Customer_Dim!$A$2:$H$501,4,0) -> Male | O1056: =VLOOKUP(C1056,Customer_Dim!$A$2:$H$501,6,0) -> Nevada | P1056: =VLOOKUP(D1056,Product_Dim!$A$1:$G$101,7,0) -> 301
A1057: SALE865 | B1057: 45770 | C1057: CUST1248 | D1057: PROD43 | E1057: =VLOOKUP(D1057,Product_Dim!$A$1:$G$101,2,0) -> USB External Hard Drive | F1057: STORE8 | G1057: 3 | H1057: 924.15 | I1057: 0.1 | J1057: PayPal | K1057: 2495.205 | L1057: =VLOOKUP(C1057,Customer_Dim!$A$2:$H$501,3,0) -> 19 | M1057: =IF(L1057<20,"Below 20", IF(L1057<40,"20–39", IF(L1057<60,"40–59","60+"))) -> Below 20 | N1057: =VLOOKUP(C1057,Customer_Dim!$A$2:$H$501,4,0) -> Male | O1057: =VLOOKUP(C1057,Customer_Dim!$A$2:$H$501,6,0) -> Nevada | P1057: =VLOOKUP(D1057,Product_Dim!$A$1:$G$101,7,0) -> 266
A1058: SALE1015 | B1058: 45725 | C1058: CUST1248 | D1058: PROD62 | E1058: =VLOOKUP(D1058,Product_Dim!$A$1:$G$101,2,0) -> Laptop Cooling Pad | F1058: STORE4 | G1058: 4 | H1058: 139.05 | I1058: 0.29 | J1058: COD | K1058: 394.902 | L1058: =VLOOKUP(C1058,Customer_Dim!$A$2:$H$501,3,0) -> 19 | M1058: =IF(L1058<20,"Below 20", IF(L1058<40,"20–39", IF(L1058<60,"40–59","60+"))) -> Below 20 | N1058: =VLOOKUP(C1058,Customer_Dim!$A$2:$H$501,4,0) -> Male | O1058: =VLOOKUP(C1058,Customer_Dim!$A$2:$H$501,6,0) -> Nevada | P1058: =VLOOKUP(D1058,Product_Dim!$A$1:$G$101,7,0) -> 222
A1059: SALE354 | B1059: 45398 | C1059: CUST1248 | D1059: PROD87 | E1059: =VLOOKUP(D1059,Product_Dim!$A$1:$G$101,2,0) -> LED Bedside Lamp | F1059: STORE8 | G1059: 4 | H1059: 289.66 | I1059: 0.25 | J1059: COD | K1059: 868.98 | L1059: =VLOOKUP(C1059,Customer_Dim!$A$2:$H$501,3,0) -> 19 | M1059: =IF(L1059<20,"Below 20", IF(L1059<40,"20–39", IF(L1059<60,"40–59","60+"))) -> Below 20 | N1059: =VLOOKUP(C1059,Customer_Dim!$A$2:$H$501,4,0) -> Male | O1059: =VLOOKUP(C1059,Customer_Dim!$A$2:$H$501,6,0) -> Nevada | P1059: =VLOOKUP(D1059,Product_Dim!$A$1:$G$101,7,0) -> 220
A1060: SALE1625 | B1060: 45569 | C1060: CUST1249 | D1060: PROD15 | E1060: =VLOOKUP(D1060,Product_Dim!$A$1:$G$101,2,0) -> 4K Home Projector | F1060: STORE7 | G1060: 3 | H1060: 326.66 | I1060: 0.28 | J1060: COD | K1060: 705.5856 | L1060: =VLOOKUP(C1060,Customer_Dim!$A$2:$H$501,3,0) -> 41 | M1060: =IF(L1060<20,"Below 20", IF(L1060<40,"20–39", IF(L1060<60,"40–59","60+"))) -> 40–59 | N1060: =VLOOKUP(C1060,Customer_Dim!$A$2:$H$501,4,0) -> Female | O1060: =VLOOKUP(C1060,Customer_Dim!$A$2:$H$501,6,0) -> New York | P1060: =VLOOKUP(D1060,Product_Dim!$A$1:$G$101,7,0) -> 301
A1061: SALE976 | B1061: 45693 | C1061: CUST1249 | D1061: PROD19 | E1061: =VLOOKUP(D1061,Product_Dim!$A$1:$G$101,2,0) -> Knee Support Brace | F1061: STORE10 | G1061: 2 | H1061: 466.42 | I1061: 0.12 | J1061: PayPal | K1061: 820.8992 | L1061: =VLOOKUP(C1061,Customer_Dim!$A$2:$H$501,3,0) -> 41 | M1061: =IF(L1061<20,"Below 20", IF(L1061<40,"20–39", IF(L1061<60,"40–59","60+"))) -> 40–59 | N1061: =VLOOKUP(C1061,Customer_Dim!$A$2:$H$501,4,0) -> Female | O1061: =VLOOKUP(C1061,Customer_Dim!$A$2:$H$501,6,0) -> New York | P1061: =VLOOKUP(D1061,Product_Dim!$A$1:$G$101,7,0) -> 65
A1062: SALE1542 | B1062: 45356 | C1062: CUST1249 | D1062: PROD48 | E1062: =VLOOKUP(D1062,Product_Dim!$A$1:$G$101,2,0) -> Car Dashboard Phone Holder | F1062: STORE7 | G1062: 3 | H1062: 855.96 | I1062: 0.29 | J1062: COD | K1062: 1823.1948 | L1062: =VLOOKUP(C1062,Customer_Dim!$A$2:$H$501,3,0) -> 41 | M1062: =IF(L1062<20,"Below 20", IF(L1062<40,"20–39", IF(L1062<60,"40–59","60+"))) -> 40–59 | N1062: =VLOOKUP(C1062,Customer_Dim!$A$2:$H$501,4,0) -> Female | O1062: =VLOOKUP(C1062,Customer_Dim!$A$2:$H$501,6,0) -> New York | P1062: =VLOOKUP(D1062,Product_Dim!$A$1:$G$101,7,0) -> 103
A1063: SALE1213 | B1063: 45809 | C1063: CUST1249 | D1063: PROD72 | E1063: =VLOOKUP(D1063,Product_Dim!$A$1:$G$101,2,0) -> Professional Jump Rope | F1063: STORE4 | G1063: 1 | H1063: 41.39 | I1063: 0.01 | J1063: Credit Card | K1063: 40.9761 | L1063: =VLOOKUP(C1063,Customer_Dim!$A$2:$H$501,3,0) -> 41 | M1063: =IF(L1063<20,"Below 20", IF(L1063<40,"20–39", IF(L1063<60,"40–59","60+"))) -> 40–59 | N1063: =VLOOKUP(C1063,Customer_Dim!$A$2:$H$501,4,0) -> Female | O1063: =VLOOKUP(C1063,Customer_Dim!$A$2:$H$501,6,0) -> New York | P1063: =VLOOKUP(D1063,Product_Dim!$A$1:$G$101,7,0) -> 300
A1064: SALE1511 | B1064: 45691 | C1064: CUST1250 | D1064: PROD55 | E1064: =VLOOKUP(D1064,Product_Dim!$A$1:$G$101,2,0) -> Ceramic Plant Pot | F1064: STORE13 | G1064: 1 | H1064: 170.68 | I1064: 0.13 | J1064: PayPal | K1064: 148.4916 | L1064: =VLOOKUP(C1064,Customer_Dim!$A$2:$H$501,3,0) -> 48 | M1064: =IF(L1064<20,"Below 20", IF(L1064<40,"20–39", IF(L1064<60,"40–59","60+"))) -> 40–59 | N1064: =VLOOKUP(C1064,Customer_Dim!$A$2:$H$501,4,0) -> Male | O1064: =VLOOKUP(C1064,Customer_Dim!$A$2:$H$501,6,0) -> Delaware | P1064: =VLOOKUP(D1064,Product_Dim!$A$1:$G$101,7,0) -> 0
A1065: SALE1641 | B1065: 45742 | C1065: CUST1250 | D1065: PROD56 | E1065: =VLOOKUP(D1065,Product_Dim!$A$1:$G$101,2,0) -> Premium Blanket Throw | F1065: STORE0 | G1065: 4 | H1065: 827.39 | I1065: 0.06 | J1065: COD | K1065: 3110.9864 | L1065: =VLOOKUP(C1065,Customer_Dim!$A$2:$H$501,3,0) -> 48 | M1065: =IF(L1065<20,"Below 20", IF(L1065<40,"20–39", IF(L1065<60,"40–59","60+"))) -> 40–59 | N1065: =VLOOKUP(C1065,Customer_Dim!$A$2:$H$501,4,0) -> Male | O1065: =VLOOKUP(C1065,Customer_Dim!$A$2:$H$501,6,0) -> Delaware | P1065: =VLOOKUP(D1065,Product_Dim!$A$1:$G$101,7,0) -> 190
A1066: SALE1323 | B1066: 45304 | C1066: CUST1251 | D1066: PROD30 | E1066: =VLOOKUP(D1066,Product_Dim!$A$1:$G$101,2,0) -> Stainless Steel Cutlery Set | F1066: STORE1 | G1066: 4 | H1066: 629.05 | I1066: 0.26 | J1066: Credit Card | K1066: 1861.988 | L1066: =VLOOKUP(C1066,Customer_Dim!$A$2:$H$501,3,0) -> 64 | M1066: =IF(L1066<20,"Below 20", IF(L1066<40,"20–39", IF(L1066<60,"40–59","60+"))) -> 60+ | N1066: =VLOOKUP(C1066,Customer_Dim!$A$2:$H$501,4,0) -> Male | O1066: =VLOOKUP(C1066,Customer_Dim!$A$2:$H$501,6,0) -> Alabama | P1066: =VLOOKUP(D1066,Product_Dim!$A$1:$G$101,7,0) -> 57
A1067: SALE1676 | B1067: 45656 | C1067: CUST1251 | D1067: PROD45 | E1067: =VLOOKUP(D1067,Product_Dim!$A$1:$G$101,2,0) -> High-Grip Football | F1067: STORE14 | G1067: 2 | H1067: 984.96 | I1067: 0.16 | J1067: PayPal | K1067: 1654.7328 | L1067: =VLOOKUP(C1067,Customer_Dim!$A$2:$H$501,3,0) -> 64 | M1067: =IF(L1067<20,"Below 20", IF(L1067<40,"20–39", IF(L1067<60,"40–59","60+"))) -> 60+ | N1067: =VLOOKUP(C1067,Customer_Dim!$A$2:$H$501,4,0) -> Male | O1067: =VLOOKUP(C1067,Customer_Dim!$A$2:$H$501,6,0) -> Alabama | P1067: =VLOOKUP(D1067,Product_Dim!$A$1:$G$101,7,0) -> 114
... A1631: SALE1769 | B1631: 45589 | C1631: CUST1403 | D1631: PROD63 | E1631: =VLOOKUP(D1631,Product_Dim!$A$1:$G$101,2,0) -> Organic Sunscreen Lotion | F1631: STORE6 | G1631: 3 | H1631: 195.89 | I1631: 0.16 | J1631: PayPal | K1631: 493.6428 | L1631: =VLOOKUP(C1631,Customer_Dim!$A$2:$H$501,3,0) -> 34 | M1631: =IF(L1631<20,"Below 20", IF(L1631<40,"20–39", IF(L1631<60,"40–59","60+"))) -> 20–39 | N1631: =VLOOKUP(C1631,Customer_Dim!$A$2:$H$501,4,0) -> Male | O1631: =VLOOKUP(C1631,Customer_Dim!$A$2:$H$501,6,0) -> Louisiana | P1631: =VLOOKUP(D1631,Product_Dim!$A$1:$G$101,7,0) -> 458
A1632: SALE58 | B1632: 45633 | C1632: CUST1404 | D1632: PROD15 | E1632: =VLOOKUP(D1632,Product_Dim!$A$1:$G$101,2,0) -> 4K Home Projector | F1632: STORE7 | G1632: 4 | H1632: 733.42 | J1632: PayPal | K1632: 2552.3016 | L1632: =VLOOKUP(C1632,Customer_Dim!$A$2:$H$501,3,0) -> 22 | M1632: =IF(L1632<20,"Below 20", IF(L1632<40,"20–39", IF(L1632<60,"40–59","60+"))) -> 20–39 | N1632: =VLOOKUP(C1632,Customer_Dim!$A$2:$H$501,4,0) -> Female | O1632: =VLOOKUP(C1632,Customer_Dim!$A$2:$H$501,6,0) -> Arkansas | P1632: =VLOOKUP(D1632,Product_Dim!$A$1:$G$101,7,0) -> 301
A1633: SALE664 | B1633: 45475 | C1633: CUST1404 | D1633: PROD16 | E1633: =VLOOKUP(D1633,Product_Dim!$A$1:$G$101,2,0) -> Beard Grooming Kit | F1633: STORE8 | G1633: 4 | H1633: 700.88 | I1633: 0.23 | J1633: PayPal | K1633: 2158.7104 | L1633: =VLOOKUP(C1633,Customer_Dim!$A$2:$H$501,3,0) -> 22 | M1633: =IF(L1633<20,"Below 20", IF(L1633<40,"20–39", IF(L1633<60,"40–59","60+"))) -> 20–39 | N1633: =VLOOKUP(C1633,Customer_Dim!$A$2:$H$501,4,0) -> Female | O1633: =VLOOKUP(C1633,Customer_Dim!$A$2:$H$501,6,0) -> Arkansas | P1633: =VLOOKUP(D1633,Product_Dim!$A$1:$G$101,7,0) -> 256
A1634: SALE452 | B1634: 45460 | C1634: CUST1404 | D1634: PROD23 | E1634: =VLOOKUP(D1634,Product_Dim!$A$1:$G$101,2,0) -> Men's Formal Shirt | F1634: STORE16 | G1634: 2 | H1634: 425.06 | I1634: 0.09 | J1634: PayPal | K1634: 773.6092 | L1634: =VLOOKUP(C1634,Customer_Dim!$A$2:$H$501,3,0) -> 22 | M1634: =IF(L1634<20,"Below 20", IF(L1634<40,"20–39", IF(L1634<60,"40–59","60+"))) -> 20–39 | N1634: =VLOOKUP(C1634,Customer_Dim!$A$2:$H$501,4,0) -> Female | O1634: =VLOOKUP(C1634,Customer_Dim!$A$2:$H$501,6,0) -> Arkansas | P1634: =VLOOKUP(D1634,Product_Dim!$A$1:$G$101,7,0) -> 360
A1635: SALE1771 | B1635: 45418 | C1635: CUST1404 | D1635: PROD79 | E1635: =VLOOKUP(D1635,Product_Dim!$A$1:$G$101,2,0) -> Decorative Lamp Shade | F1635: STORE7 | G1635: 1 | H1635: 224.49 | I1635: 0.11 | J1635: PayPal | K1635: 199.7961 | L1635: =VLOOKUP(C1635,Customer_Dim!$A$2:$H$501,3,0) -> 22 | M1635: =IF(L1635<20,"Below 20", IF(L1635<40,"20–39", IF(L1635<60,"40–59","60+"))) -> 20–39 | N1635: =VLOOKUP(C1635,Customer_Dim!$A$2:$H$501,4,0) -> Female | O1635: =VLOOKUP(C1635,Customer_Dim!$A$2:$H$501,6,0) -> Arkansas | P1635: =VLOOKUP(D1635,Product_Dim!$A$1:$G$101,7,0) -> 469
A1636: SALE1461 | B1636: 45723 | C1636: CUST1405 | D1636: PROD13 | E1636: =VLOOKUP(D1636,Product_Dim!$A$1:$G$101,2,0) -> USB-C Fast Charger | F1636: STORE10 | G1636: 1 | H1636: 120.57 | I1636: 0.06 | J1636: PayPal | K1636: 113.3358 | L1636: =VLOOKUP(C1636,Customer_Dim!$A$2:$H$501,3,0) -> 18 | M1636: =IF(L1636<20,"Below 20", IF(L1636<40,"20–39", IF(L1636<60,"40–59","60+"))) -> Below 20 | N1636: =VLOOKUP(C1636,Customer_Dim!$A$2:$H$501,4,0) -> Female | O1636: =VLOOKUP(C1636,Customer_Dim!$A$2:$H$501,6,0) -> Louisiana | P1636: =VLOOKUP(D1636,Product_Dim!$A$1:$G$101,7,0) -> 453
A1637: SALE742 | B1637: 45648 | C1637: CUST1405 | D1637: PROD18 | E1637: =VLOOKUP(D1637,Product_Dim!$A$1:$G$101,2,0) -> Women's Denim Jeans | F1637: STORE5 | G1637: 3 | H1637: 438.65 | I1637: 0.29 | J1637: PayPal | K1637: 934.3245 | L1637: =VLOOKUP(C1637,Customer_Dim!$A$2:$H$501,3,0) -> 18 | M1637: =IF(L1637<20,"Below 20", IF(L1637<40,"20–39", IF(L1637<60,"40–59","60+"))) -> Below 20 | N1637: =VLOOKUP(C1637,Customer_Dim!$A$2:$H$501,4,0) -> Female | O1637: =VLOOKUP(C1637,Customer_Dim!$A$2:$H$501,6,0) -> Louisiana | P1637: =VLOOKUP(D1637,Product_Dim!$A$1:$G$101,7,0) -> 343
A1638: SALE764 | B1638: 45745 | C1638: CUST1405 | D1638: PROD24 | E1638: =VLOOKUP(D1638,Product_Dim!$A$1:$G$101,2,0) -> Foldable Camping Chair | F1638: STORE3 | G1638: 1 | H1638: 387.99 | I1638: 0.3 | J1638: Credit Card | K1638: 271.593 | L1638: =VLOOKUP(C1638,Customer_Dim!$A$2:$H$501,3,0) -> 18 | M1638: =IF(L1638<20,"Below 20", IF(L1638<40,"20–39", IF(L1638<60,"40–59","60+"))) -> Below 20 | N1638: =VLOOKUP(C1638,Customer_Dim!$A$2:$H$501,4,0) -> Female | O1638: =VLOOKUP(C1638,Customer_Dim!$A$2:$H$501,6,0) -> Louisiana | P1638: =VLOOKUP(D1638,Product_Dim!$A$1:$G$101,7,0) -> 340
A1639: SALE1377 | B1639: 45667 | C1639: CUST1405 | D1639: PROD39 | E1639: =VLOOKUP(D1639,Product_Dim!$A$1:$G$101,2,0) -> Portable Power Bank | F1639: STORE4 | G1639: 4 | H1639: 995.4 | I1639: 0.27 | J1639: Credit Card | K1639: 2906.568 | L1639: =VLOOKUP(C1639,Customer_Dim!$A$2:$H$501,3,0) -> 18 | M1639: =IF(L1639<20,"Below 20", IF(L1639<40,"20–39", IF(L1639<60,"40–59","60+"))) -> Below 20 | N1639: =VLOOKUP(C1639,Customer_Dim!$A$2:$H$501,4,0) -> Female | O1639: =VLOOKUP(C1639,Customer_Dim!$A$2:$H$501,6,0) -> Louisiana | P1639: =VLOOKUP(D1639,Product_Dim!$A$1:$G$101,7,0) -> 301
A1640: SALE465 | B1640: 45711 | C1640: CUST1405 | D1640: PROD46 | E1640: =VLOOKUP(D1640,Product_Dim!$A$1:$G$101,2,0) -> Men's Winter Jacket | F1640: STORE9 | G1640: 1 | H1640: 83.83 | I1640: 0.05 | J1640: Credit Card | K1640: 79.6385 | L1640: =VLOOKUP(C1640,Customer_Dim!$A$2:$H$501,3,0) -> 18 | M1640: =IF(L1640<20,"Below 20", IF(L1640<40,"20–39", IF(L1640<60,"40–59","60+"))) -> Below 20 | N1640: =VLOOKUP(C1640,Customer_Dim!$A$2:$H$501,4,0) -> Female | O1640: =VLOOKUP(C1640,Customer_Dim!$A$2:$H$501,6,0) -> Louisiana | P1640: =VLOOKUP(D1640,Product_Dim!$A$1:$G$101,7,0) -> 296
A1641: SALE154 | B1641: 45613 | C1641: CUST1405 | D1641: PROD48 | E1641: =VLOOKUP(D1641,Product_Dim!$A$1:$G$101,2,0) -> Car Dashboard Phone Holder | F1641: STORE2 | G1641: 1 | H1641: 345.06 | I1641: 0.13 | J1641: COD | K1641: 300.2022 | L1641: =VLOOKUP(C1641,Customer_Dim!$A$2:$H$501,3,0) -> 18 | M1641: =IF(L1641<20,"Below 20", IF(L1641<40,"20–39", IF(L1641<60,"40–59","60+"))) -> Below 20 | N1641: =VLOOKUP(C1641,Customer_Dim!$A$2:$H$501,4,0) -> Female | O1641: =VLOOKUP(C1641,Customer_Dim!$A$2:$H$501,6,0) -> Louisiana | P1641: =VLOOKUP(D1641,Product_Dim!$A$1:$G$101,7,0) -> 103
A1642: SALE488 | B1642: 45726 | C1642: CUST1405 | D1642: PROD73 | E1642: =VLOOKUP(D1642,Product_Dim!$A$1:$G$101,2,0) -> Shin Guards – Adult | F1642: STORE13 | G1642: 4 | H1642: 922.69 | I1642: 0.16 | J1642: Credit Card | K1642: 3100.2384 | L1642: =VLOOKUP(C1642,Customer_Dim!$A$2:$H$501,3,0) -> 18 | M1642: =IF(L1642<20,"Below 20", IF(L1642<40,"20–39", IF(L1642<60,"40–59","60+"))) -> Below 20 | N1642: =VLOOKUP(C1642,Customer_Dim!$A$2:$H$501,4,0) -> Female | O1642: =VLOOKUP(C1642,Customer_Dim!$A$2:$H$501,6,0) -> Louisiana | P1642: =VLOOKUP(D1642,Product_Dim!$A$1:$G$101,7,0) -> 359
A1643: SALE1473 | B1643: 45605 | C1643: CUST1405 | D1643: PROD85 | E1643: =VLOOKUP(D1643,Product_Dim!$A$1:$G$101,2,0) -> Women's Beanie Hat | F1643: STORE18 | G1643: 2 | H1643: 227.97 | I1643: 0.08 | J1643: COD | K1643: 419.4648 | L1643: =VLOOKUP(C1643,Customer_Dim!$A$2:$H$501,3,0) -> 18 | M1643: =IF(L1643<20,"Below 20", IF(L1643<40,"20–39", IF(L1643<60,"40–59","60+"))) -> Below 20 | N1643: =VLOOKUP(C1643,Customer_Dim!$A$2:$H$501,4,0) -> Female | O1643: =VLOOKUP(C1643,Customer_Dim!$A$2:$H$501,6,0) -> Louisiana | P1643: =VLOOKUP(D1643,Product_Dim!$A$1:$G$101,7,0) -> 210
A1644: SALE91 | B1644: 45312 | C1644: CUST1406 | D1644: PROD16 | E1644: =VLOOKUP(D1644,Product_Dim!$A$1:$G$101,2,0) -> Beard Grooming Kit | F1644: STORE1 | G1644: 4 | H1644: 102.19 | I1644: 0.17 | J1644: PayPal | K1644: 339.2708 | L1644: =VLOOKUP(C1644,Customer_Dim!$A$2:$H$501,3,0) -> 23 | M1644: =IF(L1644<20,"Below 20", IF(L1644<40,"20–39", IF(L1644<60,"40–59","60+"))) -> 20–39 | N1644: =VLOOKUP(C1644,Customer_Dim!$A$2:$H$501,4,0) -> Female | O1644: =VLOOKUP(C1644,Customer_Dim!$A$2:$H$501,6,0) -> Wisconsin | P1644: =VLOOKUP(D1644,Product_Dim!$A$1:$G$101,7,0) -> 256
A1645: SALE972 | B1645: 45740 | C1645: CUST1406 | D1645: PROD3 | E1645: =VLOOKUP(D1645,Product_Dim!$A$1:$G$101,2,0) -> Men's Running Jacket | F1645: STORE16 | G1645: 1 | H1645: 402.47 | I1645: 0.19 | J1645: PayPal | K1645: 326.0007 | L1645: =VLOOKUP(C1645,Customer_Dim!$A$2:$H$501,3,0) -> 23 | M1645: =IF(L1645<20,"Below 20", IF(L1645<40,"20–39", IF(L1645<60,"40–59","60+"))) -> 20–39 | N1645: =VLOOKUP(C1645,Customer_Dim!$A$2:$H$501,4,0) -> Female | O1645: =VLOOKUP(C1645,Customer_Dim!$A$2:$H$501,6,0) -> Wisconsin | P1645: =VLOOKUP(D1645,Product_Dim!$A$1:$G$101,7,0) -> 452
A1646: SALE268 | B1646: 45555 | C1646: CUST1406 | D1646: PROD90 | E1646: =VLOOKUP(D1646,Product_Dim!$A$1:$G$101,2,0) -> Gaming Mouse Pad XL | F1646: STORE18 | G1646: 3 | I1646: 0.06 | J1646: Credit Card | K1646: 315.2478 | L1646: =VLOOKUP(C1646,Customer_Dim!$A$2:$H$501,3,0) -> 23 | M1646: =IF(L1646<20,"Below 20", IF(L1646<40,"20–39", IF(L1646<60,"40–59","60+"))) -> 20–39 | N1646: =VLOOKUP(C1646,Customer_Dim!$A$2:$H$501,4,0) -> Female | O1646: =VLOOKUP(C1646,Customer_Dim!$A$2:$H$501,6,0) -> Wisconsin | P1646: =VLOOKUP(D1646,Product_Dim!$A$1:$G$101,7,0) -> 361
A1647: SALE1343 | B1647: 45323 | C1647: CUST1406 | D1647: PROD97 | E1647: =VLOOKUP(D1647,Product_Dim!$A$1:$G$101,2,0) -> Cricket Bat | F1647: STORE1 | G1647: 3 | H1647: 760.38 | I1647: 0 | J1647: COD | K1647: 2281.14 | L1647: =VLOOKUP(C1647,Customer_Dim!$A$2:$H$501,3,0) -> 23 | M1647: =IF(L1647<20,"Below 20", IF(L1647<40,"20–39", IF(L1647<60,"40–59","60+"))) -> 20–39 | N1647: =VLOOKUP(C1647,Customer_Dim!$A$2:$H$501,4,0) -> Female | O1647: =VLOOKUP(C1647,Customer_Dim!$A$2:$H$501,6,0) -> Wisconsin | P1647: =VLOOKUP(D1647,Product_Dim!$A$1:$G$101,7,0) -> 471
A1648: SALE998 | B1648: 45522 | C1648: CUST1407 | D1648: PROD34 | E1648: =VLOOKUP(D1648,Product_Dim!$A$1:$G$101,2,0) -> Gaming Mechanical Keyboard | F1648: STORE17 | G1648: 3 | H1648: 336.17 | I1648: 0.04 | J1648: COD | K1648: 968.1696 | L1648: =VLOOKUP(C1648,Customer_Dim!$A$2:$H$501,3,0) -> 33 | M1648: =IF(L1648<20,"Below 20", IF(L1648<40,"20–39", IF(L1648<60,"40–59","60+"))) -> 20–39 | N1648: =VLOOKUP(C1648,Customer_Dim!$A$2:$H$501,4,0) -> Male | O1648: =VLOOKUP(C1648,Customer_Dim!$A$2:$H$501,6,0) -> Maryland | P1648: =VLOOKUP(D1648,Product_Dim!$A$1:$G$101,7,0) -> 86
A1649: SALE853 | B1649: 45873 | C1649: CUST1407 | D1649: PROD70 | E1649: =VLOOKUP(D1649,Product_Dim!$A$1:$G$101,2,0) -> Kitchen Storage Rack | F1649: STORE15 | G1649: 3 | H1649: 360.18 | I1649: 0.03 | J1649: Credit Card | K1649: 1048.1238 | L1649: =VLOOKUP(C1649,Customer_Dim!$A$2:$H$501,3,0) -> 33 | M1649: =IF(L1649<20,"Below 20", IF(L1649<40,"20–39", IF(L1649<60,"40–59","60+"))) -> 20–39 | N1649: =VLOOKUP(C1649,Customer_Dim!$A$2:$H$501,4,0) -> Male | O1649: =VLOOKUP(C1649,Customer_Dim!$A$2:$H$501,6,0) -> Maryland | P1649: =VLOOKUP(D1649,Product_Dim!$A$1:$G$101,7,0) -> 89
A1650: SALE60 | B1650: 45854 | C1650: CUST1408 | D1650: PROD31 | E1650: =VLOOKUP(D1650,Product_Dim!$A$1:$G$101,2,0) -> Basketball | F1650: STORE10 | G1650: 1 | H1650: 198.83 | I1650: 0.09 | J1650: COD | K1650: 180.9353 | L1650: =VLOOKUP(C1650,Customer_Dim!$A$2:$H$501,3,0) -> 36 | M1650: =IF(L1650<20,"Below 20", IF(L1650<40,"20–39", IF(L1650<60,"40–59","60+"))) -> 20–39 | N1650: =VLOOKUP(C1650,Customer_Dim!$A$2:$H$501,4,0) -> Male | O1650: =VLOOKUP(C1650,Customer_Dim!$A$2:$H$501,6,0) -> New Jersey | P1650: =VLOOKUP(D1650,Product_Dim!$A$1:$G$101,7,0) -> 281
A1651: SALE1227 | B1651: 45681 | C1651: CUST1408 | D1651: PROD59 | E1651: =VLOOKUP(D1651,Product_Dim!$A$1:$G$101,2,0) -> Men's Hair Styling Gel | F1651: STORE9 | G1651: 2 | H1651: 107.97 | I1651: 0.06 | J1651: Credit Card | K1651: 202.9836 | L1651: =VLOOKUP(C1651,Customer_Dim!$A$2:$H$501,3,0) -> 36 | M1651: =IF(L1651<20,"Below 20", IF(L1651<40,"20–39", IF(L1651<60,"40–59","60+"))) -> 20–39 | N1651: =VLOOKUP(C1651,Customer_Dim!$A$2:$H$501,4,0) -> Male | O1651: =VLOOKUP(C1651,Customer_Dim!$A$2:$H$501,6,0) -> New Jersey | P1651: =VLOOKUP(D1651,Product_Dim!$A$1:$G$101,7,0) -> 399
A1652: SALE774 | B1652: 45804 | C1652: CUST1408 | D1652: PROD84 | E1652: =VLOOKUP(D1652,Product_Dim!$A$1:$G$101,2,0) -> Wooden Bookshelf | F1652: STORE17 | G1652: 3 | H1652: 846.31 | I1652: 0.18 | J1652: COD | K1652: 2081.9226 | L1652: =VLOOKUP(C1652,Customer_Dim!$A$2:$H$501,3,0) -> 36 | M1652: =IF(L1652<20,"Below 20", IF(L1652<40,"20–39", IF(L1652<60,"40–59","60+"))) -> 20–39 | N1652: =VLOOKUP(C1652,Customer_Dim!$A$2:$H$501,4,0) -> Male | O1652: =VLOOKUP(C1652,Customer_Dim!$A$2:$H$501,6,0) -> New Jersey | P1652: =VLOOKUP(D1652,Product_Dim!$A$1:$G$101,7,0) -> 208
A1653: SALE72 | B1653: 45533 | C1653: CUST1409 | D1653: PROD38 | E1653: =VLOOKUP(D1653,Product_Dim!$A$1:$G$101,2,0) -> Sports Water Hydration Pack | F1653: STORE5 | G1653: 1 | H1653: 553.82 | I1653: 0.09 | J1653: Credit Card | K1653: 503.9762 | L1653: =VLOOKUP(C1653,Customer_Dim!$A$2:$H$501,3,0) -> 55 | M1653: =IF(L1653<20,"Below 20", IF(L1653<40,"20–39", IF(L1653<60,"40–59","60+"))) -> 40–59 | N1653: =VLOOKUP(C1653,Customer_Dim!$A$2:$H$501,4,0) -> Male | O1653: =VLOOKUP(C1653,Customer_Dim!$A$2:$H$501,6,0) -> Wyoming | P1653: =VLOOKUP(D1653,Product_Dim!$A$1:$G$101,7,0) -> 394
A1654: SALE919 | B1654: 45238 | C1654: CUST1409 | D1654: PROD70 | E1654: =VLOOKUP(D1654,Product_Dim!$A$1:$G$101,2,0) -> Kitchen Storage Rack | F1654: STORE0 | G1654: 1 | H1654: 550.06 | I1654: 0.01 | J1654: Credit Card | K1654: 544.5594 | L1654: =VLOOKUP(C1654,Customer_Dim!$A$2:$H$501,3,0) -> 55 | M1654: =IF(L1654<20,"Below 20", IF(L1654<40,"20–39", IF(L1654<60,"40–59","60+"))) -> 40–59 | N1654: =VLOOKUP(C1654,Customer_Dim!$A$2:$H$501,4,0) -> Male | O1654: =VLOOKUP(C1654,Customer_Dim!$A$2:$H$501,6,0) -> Wyoming | P1654: =VLOOKUP(D1654,Product_Dim!$A$1:$G$101,7,0) -> 89
A1655: SALE1315 | B1655: 45234 | C1655: CUST1409 | D1655: PROD71 | E1655: =VLOOKUP(D1655,Product_Dim!$A$1:$G$101,2,0) -> Hair Repair Oil Treatment | F1655: STORE15 | G1655: 2 | H1655: 985 | I1655: 0.25 | J1655: Credit Card | K1655: 1477.5 | L1655: =VLOOKUP(C1655,Customer_Dim!$A$2:$H$501,3,0) -> 55 | M1655: =IF(L1655<20,"Below 20", IF(L1655<40,"20–39", IF(L1655<60,"40–59","60+"))) -> 40–59 | N1655: =VLOOKUP(C1655,Customer_Dim!$A$2:$H$501,4,0) -> Male | O1655: =VLOOKUP(C1655,Customer_Dim!$A$2:$H$501,6,0) -> Wyoming | P1655: =VLOOKUP(D1655,Product_Dim!$A$1:$G$101,7,0) -> 383
A1656: SALE1467 | B1656: 45568 | C1656: CUST1409 | D1656: PROD9 | E1656: =VLOOKUP(D1656,Product_Dim!$A$1:$G$101,2,0) -> Adjustable Dumbbell Set | F1656: STORE8 | G1656: 3 | H1656: 136.4 | I1656: 0.15 | J1656: PayPal | K1656: 347.82 | L1656: =VLOOKUP(C1656,Customer_Dim!$A$2:$H$501,3,0) -> 55 | M1656: =IF(L1656<20,"Below 20", IF(L1656<40,"20–39", IF(L1656<60,"40–59","60+"))) -> 40–59 | N1656: =VLOOKUP(C1656,Customer_Dim!$A$2:$H$501,4,0) -> Male | O1656: =VLOOKUP(C1656,Customer_Dim!$A$2:$H$501,6,0) -> Wyoming | P1656: =VLOOKUP(D1656,Product_Dim!$A$1:$G$101,7,0) -> 323
A1657: SALE0 | B1657: 45480 | C1657: CUST1409 | D1657: PROD97 | E1657: =VLOOKUP(D1657,Product_Dim!$A$1:$G$101,2,0) -> Cricket Bat | F1657: STORE3 | G1657: 1 | H1657: 218.04 | I1657: 0.09 | J1657: Credit Card | K1657: 198.4164 | L1657: =VLOOKUP(C1657,Customer_Dim!$A$2:$H$501,3,0) -> 55 | M1657: =IF(L1657<20,"Below 20", IF(L1657<40,"20–39", IF(L1657<60,"40–59","60+"))) -> 40–59 | N1657: =VLOOKUP(C1657,Customer_Dim!$A$2:$H$501,4,0) -> Male | O1657: =VLOOKUP(C1657,Customer_Dim!$A$2:$H$501,6,0) -> Wyoming | P1657: =VLOOKUP(D1657,Product_Dim!$A$1:$G$101,7,0) -> 471
A1658: SALE1590 | B1658: 45749 | C1658: CUST1410 | D1658: PROD33 | E1658: =VLOOKUP(D1658,Product_Dim!$A$1:$G$101,2,0) -> Modern Wall Clock | F1658: STORE19 | G1658: 4 | H1658: 62.25 | I1658: 0.11 | J1658: PayPal | K1658: 221.61 | L1658: =VLOOKUP(C1658,Customer_Dim!$A$2:$H$501,3,0) -> 48 | M1658: =IF(L1658<20,"Below 20", IF(L1658<40,"20–39", IF(L1658<60,"40–59","60+"))) -> 40–59 | N1658: =VLOOKUP(C1658,Customer_Dim!$A$2:$H$501,4,0) -> Female | O1658: =VLOOKUP(C1658,Customer_Dim!$A$2:$H$501,6,0) -> New Jersey | P1658: =VLOOKUP(D1658,Product_Dim!$A$1:$G$101,7,0) -> 305
... A2001: SALE177 | B2001: 45670 | C2001: CUST1499 | D2001: PROD55 | E2001: =VLOOKUP(D2001,Product_Dim!$A$1:$G$101,2,0) -> Ceramic Plant Pot | F2001: STORE8 | G2001: 1 | H2001: 79 | I2001: 0.04 | J2001: PayPal | K2001: 75.84 | L2001: =VLOOKUP(C2001,Customer_Dim!$A$2:$H$501,3,0) -> 27 | M2001: =IF(L2001<20,"Below 20", IF(L2001<40,"20–39", IF(L2001<60,"40–59","60+"))) -> 20–39 | N2001: =VLOOKUP(C2001,Customer_Dim!$A$2:$H$501,4,0) -> Female | O2001: =VLOOKUP(C2001,Customer_Dim!$A$2:$H$501,6,0) -> Oregon | P2001: =VLOOKUP(D2001,Product_Dim!$A$1:$G$101,7,0) -> 0

Sheet Age group - Gender - Sales
A1: Row Labels | B1: Sum of Total_Amount | E1: Row Labels | F1: Sum of Total_Amount
A2: 20–39 | B2: 876431.3 | E2: Female | F2: 1231444.2
A3: 40–59 | B3: 975956.55 | E3: Male | F3: 942950.47
A4: 60+ | B4: 242004.56 | E4: Grand Total | F4: 2174394.7
A5: Below 20 | B5: 80002.295
A6: Grand Total | B6: 2174394.7

Sheet Year - Sales
A1: Row Labels | B1: Sum of Total_Amount
A2: 2023 | B2: 223812.72
A3: 2024 | B3: 1093911.8
A4: 2025 | B4: 856670.18
A5: Grand Total | B5: 2174394.7

Sheet Product Sales Dashboard
A1: PRODUCT SALES DASHBOARD

Sheet Summary & Key Insights
